Workbook

Sheet Sheet1
B3: Column Labels
B4: 2023 | J4: 2023 Total | K4: 2024 | W4: 2024 Total | X4: 2025 | AE4: 2025 Total | AF4: Grand Total
B5: May | C5: Jun | D5: Jul | E5: Aug | F5: Sep | G5: Oct | H5: Nov | I5: Dec | K5: Jan | L5: Feb | M5: Mar | N5: Apr | O5: May | P5: Jun | Q5: Jul | R5: Aug | S5: Sep | T5: Oct | U5: Nov | V5: Dec | X5: Jan | Y5: Feb | Z5: Mar | AA5: Apr | AB5: May | AC5: Jun | AD5: Jul
A6: Count of Serial Number | B6: 12 | C6: 76 | D6: 56 | E6: 86 | F6: 108 | G6: 98 | H6: 92 | I6: 160 | J6: 688 | K6: 125 | L6: 68 | M6: 103 | N6: 98 | O6: 105 | P6: 104 | Q6: 64 | R6: 80 | S6: 88 | T6: 84 | U6: 69 | V6: 115 | W6: 1103 | X6: 68 | Y6: 69 | Z6: 83 | AA6: 91 | AB6: 79 | AC6: 104 | AD6: 73 | AE6: 567 | AF6: 2358

Sheet Sheet3
A3: Row Labels | B3: Count of Dealer Name
A4: Abhishek Megamech Private Limited-C14753-BLC, FARIDABAD, HP | B4: 1
A5: Advantage Farm Equipment Ltd, Wyoming, ON-01520, Wyoming, ON | B5: 1
A6: Ag-Plus Mechanical Ltd., Medicine Hat, AB-00070, MEDICINE HAT, AB | B6: 1
A7: Agrikom, Mirabel, QC-00302, Mirabel, QC | B7: 1
A8: ASHA INFRACORE-C07923-BC, BANGALORE, KARNATAKA | B8: 2
A9: ASHA INFRACORE-C07923-BLC, Bangalore | B9: 1
A10: Atlas Bobcat, Elk Grove Village, IL-00450, ELK GROVE VILLAGE, IL | B10: 1
A11: Atlas Bobcat, Elk Grove Village., IL-00450, ELK GROVE VILLAGE, IL | B11: 16
A12: Atlas Bobcat, Mokena, IL-00275, MOKENA, IL | B12: 7
A13: Atlas Bobcat, Wauconda, IL-02198, WAUCONDA, IL | B13: 3
A14: Atlas Bobcat, West Chicago, IL-00306, WEST CHICAGO, IL | B14: 3
A15: Berchtold Equipment Co, Bakersfield, CA-00927, BAKERSFIELD, CA | B15: 18
... A512: Grand Total | B512: 2358

Sheet IRW missings
A1: IRW not added m/c no | E1: Deler side not rental
A2: B5Y211823 | E2: B5Y211049 | R2: B5Y211309
A3: B5Y212444 | E3: B5Y211066 | R3: B5Y211401
A4: B5Y213315 | E4: B5Y211086 | R4: B5Y211421
A5: B5Y213419 | E5: B5Y211114 | R5: B5Y211489
A6: B5Y213646 | E6: B5Y211123 | R6: B5Y211498
A7: B5Y213709 | E7: B5Y211228 | R7: B5Y211520
A8: B5Y213773 | E8: B5Y211251 | R8: B5Y211524
A9: B5Y213789 | E9: B5Y211348 | R9: B5Y211535
A10: B5Y213876 | E10: B5Y211452 | R10: B5Y211555
A11: B5Y213887 | E11: B5Y211474 | R11: B5Y211558
A12: B5Y213927 | E12: B5Y211629 | R12: B5Y211580
A13: B5Y213953 | E13: B5Y211658 | R13: B5Y211630
... A38: DBIB5Y2GCR0012753 | E38: B5Y212236 | R38: B5Y212004
E39: B5Y212239 | R39: B5Y212028
E40: B5Y212241 | R40: B5Y212034
E41: B5Y212261 | R41: B5Y212036
E42: B5Y212287 | R42: B5Y212039
E43: B5Y212305 | R43: B5Y212041
E44: B5Y212322 | R44: B5Y212042
E45: B5Y212347 | R45: B5Y212043
E46: B5Y212354 | R46: B5Y212044
E47: B5Y212366 | R47: B5Y212045
E48: B5Y212374 | R48: B5Y212046
E49: B5Y212377 | R49: B5Y212047
E50: B5Y212402 | R50: B5Y212048
... E144: B5Y214001 | R144: B5Y212784
E145: B5Y214003 | I145: IRW = 1335 ORACLE = 1276 DIFF=59 MATCH=1239 UNMATCH=37 | R145: B5Y212789
E146: B5Y214007 | R146: B5Y212790
E147: B5Y214008 | R147: B5Y212835
E148: B5Y214010 | R148: B5Y212842
E149: B5Y214015 | R149: B5Y212843
E150: B5Y214016 | R150: B5Y212844
E151: B5Y214017 | R151: B5Y212845
E152: B5Y214018 | R152: B5Y212857
E153: B5Y214023 | R153: B5Y212860
E154: B5Y214025 | R154: B5Y212869
E155: B5Y214028 | R155: B5Y212884
E156: B5Y214029 | R156: B5Y212886
E157: B5Y214030 | R157: B5Y212888
... E233: DBIB5Y2GKR0013308 | R233: B5Y213123
R234: B5Y213124
R235: B5Y213128
E236: B5Y211823 | R236: B5Y213129
E237: B5Y212444 | R237: B5Y213130
E238: B5Y213315 | R238: B5Y213131
E239: B5Y213419 | R239: B5Y213132
E240: B5Y213646 | R240: B5Y213136
E241: B5Y213709 | R241: B5Y213138
E242: B5Y213773 | R242: B5Y213139
E243: B5Y213789 | R243: B5Y213140
E244: B5Y213876 | R244: B5Y213141
E245: B5Y213887 | R245: B5Y213143
E246: B5Y213927 | R246: B5Y213144
E247: B5Y213953 | R247: B5Y213145
... E272: DBIB5Y2GCR0012753 | R272: B5Y213179
R273: B5Y213180
R274: B5Y213181
R275: B5Y213182
R276: B5Y213183
R277: B5Y213185
R278: B5Y213186
R279: B5Y213187
R280: B5Y213188
R281: B5Y213189
R282: B5Y213191
R283: B5Y213192
R284: B5Y213195
... R2446: DBIB5Y2GTS0013392

Sheet Delear Rental
A1: Serial Number | B1: Model | C1: Dealer Name | D1: Customer Name | E1: Customer Type | F1: Date of Delivery | G1: Download Date
A2: B5Y211114 | B2: S70 T4 V2 | C2: DNF, INC. BOBCAT OF SACRAMENTO-2000007774, SACRAMENTO, CA | D2: DNF, INC. BOBCAT OF SACRAMENTO-2000007774, SACRAMENTO, CA | E2: DEALERSHIP | F2: 07/07/2023
A3: B5Y211348 | B3: S70 T4 V2 | C3: BERRY COMPANIES, INC. BOBCAT OF NORTH TEXAS-LEWISVILLE-2000008213, LEWISVILLE, TX | D3: BERRY COMPANIES, INC. BOBCAT OF NORTH TEXAS-LEWISVILLE-2000008213, LEWISVILLE, TX | E3: DEALERSHIP | F3: 08/08/2023
A4: B5Y211251 | B4: S70 T4 V2 | C4: LEPPO, INC. BOBCAT OF CLEVELAND-BEDFORD HEIGHTS-4000010016, BEDFORD HEIGHTS, OH | D4: LEPPO, INC. BOBCAT OF CLEVELAND-BEDFORD HEIGHTS-4000010016, BEDFORD HEIGHTS, OH | E4: DEALERSHIP | F4: 09/21/2023
A5: B5Y211123 | B5: S70 T4 V2 | C5: LEPPO, INC. BOBCAT OF CLEVELAND-BEDFORD HEIGHTS-4000010016, BEDFORD HEIGHTS, OH | D5: LEPPO, INC. BOBCAT OF CLEVELAND-BEDFORD HEIGHTS-4000010016, BEDFORD HEIGHTS, OH | E5: DEALERSHIP | F5: 09/21/2023
A6: B5Y211049 | B6: S70 T4 V2 | C6: CARLETON EQUIPMENT COMPANY BOBCAT OF MOTOR CITY-LIVONIA-2000007759, LIVONIA, MI | D6: CARLETON EQUIPMENT COMPANY BOBCAT OF MOTOR CITY-LIVONIA-2000007759, LIVONIA, MI | E6: DEALERSHIP | F6: 11/14/2023
A7: B5Y211066 | B7: S70 T4 V2 | C7: DNF, INC. BOBCAT OF FRESNO-2000007705, FRESNO, CA | D7: DNF, INC. BOBCAT OF FRESNO-2000007705, FRESNO, CA | E7: DEALERSHIP | F7: 06/23/2023
A8: B5Y211086 | B8: S70 T4 V2 | C8: TRINITY VENTURE PARTNERS, LLC. BOBCAT OF HONOLULU-2000008048, HONOLULU, HI | D8: OLD - Service Rentals & Supplies, Hilo, HI-MATSON, HILO, HI_110000095218064_DEACTIVATED | E8: DEALERSHIP | F8: 06/14/2023
A9: B5Y212164 | B9: S70 T4 V2 | C9: BOBCAT OF CHICO INC. ICONIC MACHINERY- PITTSBURG-4000015379, PITTSBURG, CA | D9: OLD - TOTAL EQUIP & RENTAL OF THE W BOBCAT OF CONTRA COSTA-2000007772, PITTSBURG, CA | E9: DEALERSHIP | F9: 04/11/2024
A10: B5Y211658 | B10: S70 T4 V2 | C10: BINGHAM EQUIPMENT COMPANY -TUSCON-4000011938, TUCSON, AZ | D10: BINGHAM EQUIPMENT COMPANY -TUSCON-4000011938, TUCSON, AZ | E10: DEALERSHIP | F10: 06/10/2024
A11: B5Y212112 | B11: S70 T4 V2 | C11: BERRY COMPANIES, INC. BOBCAT OF NORTH TEXAS-LEWISVILLE-2000008213, LEWISVILLE, TX | D11: BERRY COMPANIES, INC. BOBCAT OF NORTH TEXAS-LEWISVILLE-2000008213, LEWISVILLE, TX | E11: DEALERSHIP | F11: 01/30/2024
A12: B5Y212121 | B12: S70 T4 V2 | C12: BOBCAT OF CHICO INC. ICONIC MACHINERY- GILROY-4000015932, GILROY, CA | D12: OLD - TOTAL EQUIP & RENTAL OF THE W BOBCAT OF GILROY-2000007824, GILROY, CA | E12: DEALERSHIP | F12: 02/08/2024
A13: B5Y212105 | B13: S70 T4 V2 | C13: BOBCAT OF CHICO INC. ICONIC MACHINERY- REDDING-2000008196, REDDING, CA | D13: BOBCAT OF CHICO INC. ICONIC MACHINERY- REDDING-2000008196, REDDING, CA | E13: DEALERSHIP | F13: 03/31/2024
... A104: B5Y212241 | B104: S70 T4 V2 | C104: BINGHAM EQUIPMENT COMPANY -CASA GRANDE-4000012072, CASA GRANDE, AZ | D104: BINGHAM EQUIPMENT COMPANY -CASA GRANDE-4000012072, CASA GRANDE, AZ | E104: DEALERSHIP | F104: 06/10/2024
A107: B5Y211305
A108: B5Y211362
A109: B5Y211411
A110: B5Y211541
A111: B5Y211579
A112: B5Y211694
A113: B5Y211721
A114: B5Y211754
A115: B5Y211768
A116: B5Y211775
A117: B5Y211782
A118: B5Y211804
... A1358: DBIB5Y2GTS0013392

Sheet S70Sheet
A1: Serial Number | B1: Model | C1: Dealer Name | D1: Customer Name | E1: Customer Type | F1: Date of Delivery | G1: Download Date | H1: Salesperson | I1: Country/region2
A2: B5Y211008 | B2: S70 T4 V2 | C2: Miramar Bobcat, San Diego, CA-06877, SAN DIEGO, CA | D2: HERNANDEZ BROTHERS LANDSCAPING | E2: CUSTOMER | F2: 45070 | G2: 45077 | H2: Matthew Jarvis
A3: B5Y211013 | B3: S70 T4 V2 | C3: SUNBELT RENTALS - PC0133-N000300, Decatur, AL | D3: SUNBELT RENTALS - PC0133-N000300, Decatur, AL | E3: NATIONALACCOUNT | F3: 45061 | G3: 45077
A4: B5Y211015 | B4: S70 T4 V2 | C4: South Coast Bobcat, Orange, CA-08461, ORANGE, CA | D4: Instant Hauling | E4: CUSTOMER | F4: 45071 | G4: 45077 | H4: Dan Arevalo
A5: B5Y211028 | B5: S70 T4 V2 | C5: Valley Bobcat, Sun Valley, CA-09467, SUN VALLEY, CA | D5: Charlie & Sons Trucking | E5: CUSTOMER | F5: 45070 | G5: 45077 | H5: Jonpierre Rejas
A6: B5Y211031 | B6: S70 T4 V2 | C6: Inland Bobcat, Riverside, CA-03080, RIVERSIDE, CA | D6: Ready Equipment Rental | E6: CUSTOMER | F6: 45063 | G6: 45077 | H6: Hector Sanchez
A7: B5Y211032 | B7: S70 T4 V2 | C7: Valley Bobcat, Sun Valley, CA-09467, SUN VALLEY, CA | D7: Server Construction, Inc. | E7: CUSTOMER | F7: 45069 | G7: 45077 | H7: Jonpierre Rejas
A8: B5Y211036 | B8: S70 T4 V2 | C8: Bobcat of the Rockies, Colorado Springs, CO-00528, COLORADO SPRINGS, CO | D8: BILLS TOOL RENTAL | E8: CUSTOMER | F8: 45071 | G8: 45077 | H8: Daniel Hankins
A9: B5Y211065 | B9: S70 T4 V2 | C9: Bobcat of the Rockies, Colorado Springs, CO-00528, COLORADO SPRINGS, CO | D9: BILLS TOOL RENTAL | E9: CUSTOMER | F9: 45071 | G9: 45077 | H9: Daniel Hankins
A10: B5Y211067 | B10: S70 T4 V2 | C10: Berchtold Equipment Co, Bakersfield, CA-00927, BAKERSFIELD, CA | D10: DO IT BEST - 6089-N106960, Rosamond, CA | E10: NATIONALACCOUNT | F10: 45064 | G10: 45077 | H10: Terry Spencer
A11: B5Y211085 | B11: S70 T4 V2 | C11: Bobcat of Ventura, Ventura, CA-08744, VENTURA, CA | D11: Antonio Benitez Landscape | E11: CUSTOMER | F11: 45071 | G11: 45077 | H11: Randy Dvorak
A12: B5Y211100 | B12: S70 T4 V2 | C12: Bobcat of Eugene, Eugene, OR-07130, EUGENE, OR | D12: Zoltan Molar | E12: CUSTOMER | F12: 45066 | G12: 45077 | H12: Brandon Weaver
A13: B5Y211104 | B13: S70 T4 V2 | C13: Bobcat of Gilroy, Gilroy, CA-02814, GILROY, CA | D13: Quynh Ngo | E13: CUSTOMER | F13: 45069 | G13: 45077 | H13: Alex Serdiuk
A14: B5Y211007 | B14: S70 T4 V2 | C14: Bobcat of Las Vegas, North Las Vegas, NV-01127, NORTH LAS VEGAS, NV | D14: Medel Repairs LLC. | E14: CUSTOMER | F14: 45091 | G14: 45104 | H14: Carlo Damelio
A15: B5Y211010 | B15: S70 T4 V2 | C15: Bobcat of Las Vegas, North Las Vegas, NV-01127, NORTH LAS VEGAS, NV | D15: GREENSCAPES OF NEVADA LLC. | E15: CUSTOMER | F15: 45093 | G15: 45104 | H15: Carlo Damelio
... A89: B5Y211369 | B89: S70 T4 V2 | C89: ASHA INFRACORE-C07923-BC, BANGALORE, KARNATAKA | D89: KIOCL LIMITED | E89: CUSTOMER | F89: 45103 | G89: 45107 | H89: Chetana Kalmane
A90: B5Y211006 | B90: S70 T4 V2 | C90: SUNSTATE EQUIPMENT - DNV-N002683, Commerce City, CO | D90: SUNSTATE EQUIPMENT - DNV-N002683, Commerce City, CO | E90: NATIONALACCOUNT | F90: 45134 | G90: 45138
A91: B5Y211039 | B91: S70 T4 V2 | C91: Bobcat of Calgary, Calgary, AB-07983, CALGARY, AB | D91: THE RENTAL GUYS.CA - CALGARY-N103500, Calgary, AB | E91: NATIONALACCOUNT | F91: 45125 | G91: 45138 | H91: Ashley Beames
A92: B5Y211042 | B92: S70 T4 V2 | C92: Sooland Bobcat, Sioux City, IA-02324, SIOUX CITY, IA | D92: Martin Diaz | E92: CUSTOMER | F92: 45113 | G92: 45138 | H92: Kevin Powell
A93: B5Y211052 | B93: S70 T4 V2 | C93: Bobcat of Toronto, Scarborough, ON-04218, SCARBOROUGH, ON | D93: Cooper Equipment Rentals Inc. | E93: CUSTOMER | F93: 45135 | G93: 45138 | H93: Kai Sorensen
A94: B5Y211059 | B94: S70 T4 V2 | C94: Bingham Equipment Co, Mesa, AZ-01056, MESA, AZ | D94: A to Z Equipment Rentals | E94: CUSTOMER | F94: 45105 | G94: 45138 | H94: Nate Stanton
A95: B5Y211071 | B95: S70 T4 V2 | C95: Bobcat of Houston/Pearland, Houston, TX-00553, HOUSTON, TX | D95: TNT TRACTOR RENTALS LLC | E95: CUSTOMER | F95: 45126 | G95: 45138 | H95: Josh Kimich
A96: B5Y211078 | B96: S70 T4 V2 | C96: Machineries Trakto, Laval, QC-00225, LAVAL, QC | D96: Delsan-Aim | E96: CUSTOMER | F96: 45111 | G96: 45138 | H96: Stevens Parker
A97: B5Y211081 | B97: S70 T4 V2 | C97: SUNSTATE EQUIPMENT - BWP-N95511, Baldwin Park, CA | D97: SUNSTATE EQUIPMENT - BWP-N95511, Baldwin Park, CA | E97: NATIONALACCOUNT | F97: 45078 | G97: 45138
A98: B5Y211090 | B98: S70 T4 V2 | C98: Bobcat of Contra Costa, Pittsburg, CA-01845, PITTSBURG, CA | D98: JAC CONSTRUCTION | E98: CUSTOMER | F98: 45121 | G98: 45138 | H98: Jay Alias
A99: B5Y211096 | B99: S70 T4 V2 | C99: Bobcat of Amarillo, Amarillo, TX-07302, AMARILLO, TX | D99: COLT MOLLOY | E99: CUSTOMER | F99: 45118 | G99: 45138 | H99: Rick Trejo
A100: B5Y211097 | B100: S70 T4 V2 | C100: SUNSTATE EQUIPMENT - BEN-N105256, Benicia, CA | D100: SUNSTATE EQUIPMENT - BEN-N105256, Benicia, CA | E100: NATIONALACCOUNT | F100: 45138 | G100: 45138 | H100: Warranty Admin
A101: B5Y211102 | B101: S70 T4 V2 | C101: SUNSTATE EQUIPMENT - BWP-N95511, Baldwin Park, CA | D101: SUNSTATE EQUIPMENT - BWP-N95511, Baldwin Park, CA | E101: NATIONALACCOUNT | F101: 45078 | G101: 45138
A102: B5Y211103 | B102: S70 T4 V2 | C102: SUNSTATE EQUIPMENT - PEO-N002423, Peoria, AZ | D102: SUNSTATE EQUIPMENT - PEO-N002423, Peoria, AZ | E102: NATIONALACCOUNT | F102: 45082 | G102: 45138
A103: B5Y211112 | B103: S70 T4 V2 | C103: Bobcat of Goleta, Goleta, CA-08743, GOLETA, CA | D103: Centerpoint | E103: CUSTOMER | F103: 45107 | G103: 45138 | H103: Jeff Wright
A104: B5Y211113 | B104: S70 T4 V2 | C104: SUNSTATE EQUIPMENT - DNV-N002683, Commerce City, CO | D104: SUNSTATE EQUIPMENT - DNV-N002683, Commerce City, CO | E104: NATIONALACCOUNT | F104: 45077 | G104: 45138
A105: B5Y211115 | B105: S70 T4 V2 | C105: Bobcat of El Paso, El Paso, TX-00573, EL PASO, TX | D105: Southwest Trucks and Equipment | E105: CUSTOMER | F105: 45086 | G105: 45138 | H105: James Napier
A106: B5Y211119 | B106: S70 T4 V2 | C106: Bobcat of Marble Falls, Marble Falls, TX-07305, Marble Falls, TX | D106: Casaperior, LLC. | E106: CUSTOMER | F106: 45120 | G106: 45138 | H106: Danny Lopez
A107: B5Y211128 | B107: S70 T4 V2 | C107: Bobcat of Salem, Salem, OR-02108, SALEM, OR | D107: Covanta-Marion County | E107: CUSTOMER | F107: 45114 | G107: 45138 | H107: Nathan Leao
A108: B5Y211131 | B108: S70 T4 V2 | C108: SUNSTATE EQUIPMENT - TUC-N002782, Tucson, AZ | D108: SUNSTATE EQUIPMENT - TUC-N002782, Tucson, AZ | E108: NATIONALACCOUNT | F108: 45082 | G108: 45138
A109: B5Y211133 | B109: S70 T4 V2 | C109: Bobcat of Sacramento, Sacramento, CA-01873, SACRAMENTO, CA | D109: MARTIN MARTINEZ PADILLA | E109: CUSTOMER | F109: 45128 | G109: 45138 | H109: Randy Erwin
A110: B5Y211135 | B110: S70 T4 V2 | C110: SUNSTATE EQUIPMENT - BWP-N95511, Baldwin Park, CA | D110: SUNSTATE EQUIPMENT - BWP-N95511, Baldwin Park, CA | E110: NATIONALACCOUNT | F110: 45078 | G110: 45138
A111: B5Y211137 | B111: S70 T4 V2 | C111: SUNSTATE EQUIPMENT - VEG-N002652, Henderson, NV | D111: SUNSTATE EQUIPMENT - VEG-N002652, Henderson, NV | E111: NATIONALACCOUNT | F111: 45083 | G111: 45138
A112: B5Y211141 | B112: S70 T4 V2 | C112: Inland Bobcat, Riverside, CA-03080, RIVERSIDE, CA | D112: JRC CONSTRUCTION | E112: CUSTOMER | F112: 45117 | G112: 45138 | H112: Art Mata
A113: B5Y211143 | B113: S70 T4 V2 | C113: Inland Bobcat, Riverside, CA-03080, RIVERSIDE, CA | D113: RUBEN FUNES | E113: CUSTOMER | F113: 45117 | G113: 45138 | H113: Art Mata
A114: B5Y211144 | B114: S70 T4 V2 | C114: Bingham Equipment Co, Mesa, AZ-01056, MESA, AZ | D114: Creative Landscape Images, LLC | E114: CUSTOMER | F114: 45135 | G114: 45138 | H114: Nate Stanton
A115: B5Y211146 | B115: S70 T4 V2 | C115: Bobcat of Houston, Houston, TX-00521, HOUSTON, TX | D115: TNT TRACTOR RENTALS LLC | E115: CUSTOMER | F115: 45126 | G115: 45138 | H115: Josh Kimich
A116: B5Y211149 | B116: S70 T4 V2 | C116: Bingham Equipment Co, Mesa, AZ-01056, MESA, AZ | D116: CREATIVE DESIGN LANDSCAPE | E116: CUSTOMER | F116: 45128 | G116: 45138 | H116: Nate Stanton
A117: B5Y211151 | B117: S70 T4 V2 | C117: Bingham Equipment Co, Mesa, AZ-01056, MESA, AZ | D117: CREATIVE DESIGN LANDSCAPE | E117: CUSTOMER | F117: 45128 | G117: 45138 | H117: Nate Stanton
A118: B5Y211152 | B118: S70 T4 V2 | C118: Bingham Equipment Co, Mesa, AZ-01056, MESA, AZ | D118: A to Z Equipment Rentals | E118: CUSTOMER | F118: 45105 | G118: 45138 | H118: Nate Stanton
A119: B5Y211155 | B119: S70 T4 V2 | C119: Bobcat of Phoenix, Phoenix, AZ-01055, PHOENIX, AZ | D119: Topos Construction And Landscaping LLC | E119: CUSTOMER | F119: 45125 | G119: 45138 | H119: Daniel Hernandez
A120: B5Y211156 | B120: S70 T4 V2 | C120: Bobcat of Phoenix, Phoenix, AZ-01055, PHOENIX, AZ | D120: LL & G LLC | E120: CUSTOMER | F120: 45125 | G120: 45138 | H120: Gary Walker
A121: B5Y211158 | B121: S70 T4 V2 | C121: Bingham Equipment Co, Mesa, AZ-01056, MESA, AZ | D121: A to Z Equipment Rentals | E121: CUSTOMER | F121: 45105 | G121: 45138 | H121: Nate Stanton
A122: B5Y211160 | B122: S70 T4 V2 | C122: Bobcat of Phoenix, Phoenix, AZ-01055, PHOENIX, AZ | D122: Deer Valley Pavers LLC | E122: CUSTOMER | F122: 45114 | G122: 45138 | H122: Gary Walker
A123: B5Y211163 | B123: S70 T4 V2 | C123: Bingham Equipment Co, Mesa, AZ-01056, MESA, AZ | D123: Unique Rock & Water, Inc. | E123: CUSTOMER | F123: 45131 | G123: 45138 | H123: Ashley Ghose
... A134: B5Y211196 | B134: S70 T4 V2 | C134: KARM SALES & SERVICE-C10750-BC, RAIPUR, CHHATTISGARH | D134: M/S SHAPOORJI PALLONJI | E134: CUSTOMER | F134: 45113 | G134: 45138 | H134: Altaf Khan
A135: B5Y211219 | B135: S70 T4 V2 | C135: SUNBELT RENTALS - PC0052-N000310, Spartanburg, SC | D135: SUNBELT RENTALS - PC0052-N000310, Spartanburg, SC | E135: NATIONALACCOUNT | F135: 45132 | G135: 45138
A136: B5Y211229 | B136: S70 T4 V2 | C136: Bobcat of North Texas - Fort Worth, Fort Worth, TX-00657, FORT WORTH, TX | D136: Taylor Rental Equipment | E136: CUSTOMER | F136: 45135 | G136: 45138 | H136: TRENT WALKER
A137: B5Y211244 | B137: S70 T4 V2 | C137: Inland Bobcat, Riverside, CA-03080, RIVERSIDE, CA | D137: Geovany Camacho | E137: CUSTOMER | F137: 45133 | G137: 45138 | H137: Art Mata
A138: B5Y211255 | B138: S70 T4 V2 | C138: SUNBELT RENTALS - PC1210-N106368, Warrendale, PA | D138: SUNBELT RENTALS - PC1210-N106368, Warrendale, PA | E138: NATIONALACCOUNT | F138: 45132 | G138: 45138
A139: B5Y211258 | B139: S70 T4 V2 | C139: SUNBELT RENTALS - PC0663-N102935, Bakersfield, CA | D139: SUNBELT RENTALS - PC0663-N102935, Bakersfield, CA | E139: NATIONALACCOUNT | F139: 45133 | G139: 45138
A140: B5Y211262 | B140: S70 T4 V2 | C140: SUNBELT RENTALS - PC0178-N000360, Hunt Valley, MD | D140: SUNBELT RENTALS - PC0178-N000360, Hunt Valley, MD | E140: NATIONALACCOUNT | F140: 45138 | G140: 45138
A141: B5Y211263 | B141: S70 T4 V2 | C141: SUNBELT RENTALS - PC1001-N103515, El Mirage, AZ | D141: SUNBELT RENTALS - PC1001-N103515, El Mirage, AZ | E141: NATIONALACCOUNT | F141: 45131 | G141: 45138
A142: B5Y211265 | B142: S70 T4 V2 | C142: SUNBELT RENTALS - PC0164-N000864, Swedesboro, NJ | D142: SUNBELT RENTALS - PC0164-N000864, Swedesboro, NJ | E142: NATIONALACCOUNT | F142: 45133 | G142: 45138
A143: B5Y211268 | B143: S70 T4 V2 | C143: Bingham Equipment Co, Mesa, AZ-01056, MESA, AZ | D143: EZEQUIEL HERNANDEZ | E143: CUSTOMER | F143: 45135 | G143: 45138 | H143: Ashley Ghose
A144: B5Y211274 | B144: S70 T4 V2 | C144: Bingham Equipment Co, Mesa, AZ-01056, MESA, AZ | D144: Arizona Yard Maintenance LLC | E144: CUSTOMER | F144: 45135 | G144: 45138 | H144: Brandon Townsend
A145: B5Y211455 | B145: S70 T4 V2 | C145: MARWELL COMPRESSORS AND EQQUIPMENTS INDIA PVT LTD-C02756-BLC, Coimbatore, Tamil Nadu | D145: SURYADEV ALLOYS AND POWER PVT LTD | E145: CUSTOMER | F145: 45127 | G145: 45138 | H145: BHL Purchase
A146: B5Y211034 | B146: S70 T4 V2 | C146: Bobcat of Lakeland, Lakeland, FL-08946, LAKELAND, FL | D146: RINKER MATERIALS | E146: CUSTOMER | F146: 45159 | G146: 45169
A147: B5Y211044 | B147: S70 T4 V2 | C147: Bobcat of West Chester, West Chester, PA-00280, WEST CHESTER, PA | D147: Rich Industrial Services Inc. | E147: CUSTOMER | F147: 45147 | G147: 45169
A148: B5Y211048 | B148: S70 T4 V2 | C148: Bobcat of Philadelphia, Warminster, PA-00965, WARMINSTER, PA | D148: Bello Brothers Construction | E148: CUSTOMER | F148: 07/26/2023 | G148: 45169
A149: B5Y211054 | B149: S70 T4 V2 | C149: UNITED RENTALS 801-N96333, Everett, MA | D149: UNITED RENTALS 801-N96333, Everett, MA | E149: NATIONALACCOUNT | F149: 08/08/2023 | G149: 45169
A150: B5Y211063 | B150: S70 T4 V2 | C150: Bobcat of San Antonio, San Antonio, TX-07742, SAN ANTONIO, TX | D150: Robles 1, LLC | E150: CUSTOMER | F150: 08/25/2023 | G150: 45169
A151: B5Y211099 | B151: S70 T4 V2 | C151: Miramar Bobcat, San Diego, CA-06877, SAN DIEGO, CA | D151: Alex Macias | E151: CUSTOMER | F151: 08/03/2023 | G151: 45169
A152: B5Y211126 | B152: S70 T4 V2 | C152: Bingham Equipment Co, Tucson, AZ-01075, TUCSON, AZ | D152: SANTA RITA LANDSCAPING | E152: CUSTOMER | F152: 07/31/2023 | G152: 45169
A153: B5Y211139 | B153: S70 T4 V2 | C153: Bobcat of Fresno, Fresno, CA-01119, FRESNO, CA | D153: SALAS CONCRETE | E153: CUSTOMER | F153: 08/24/2023 | G153: 45169
A154: B5Y211140 | B154: S70 T4 V2 | C154: Bobcat of Richmond, Ashland, VA-09758, ASHLAND, VA | D154: RENTAL STORES LLC | E154: CUSTOMER | F154: 08/09/2023 | G154: 45169
A155: B5Y211147 | B155: S70 T4 V2 | C155: Bobcat of Santa Rosa, Santa Rosa, CA-00632, SANTA ROSA, CA | D155: G Family Leasing LLC | E155: CUSTOMER | F155: 08/03/2023 | G155: 45169
A156: B5Y211150 | B156: S70 T4 V2 | C156: Bingham Equipment Co, Buckeye, AZ-01068, BUCKEYE, AZ | D156: Circle B leasing, LLC | E156: CUSTOMER | F156: 08/26/2023 | G156: 45169
A157: B5Y211169 | B157: S70 T4 V2 | C157: Bobcat of Los Angeles., Cerritos, CA-06879, CERRITOS, CA | D157: Quality Rentals | E157: CUSTOMER | F157: 08/17/2023 | G157: 45169
A158: B5Y211170 | B158: S70 T4 V2 | C158: Bobcat of Los Angeles., Cerritos, CA-06879, CERRITOS, CA | D158: Quality Rentals | E158: CUSTOMER | F158: 08/17/2023 | G158: 45169
A159: B5Y211171 | B159: S70 T4 V2 | C159: Bobcat of Las Vegas, North Las Vegas, NV-01127, NORTH LAS VEGAS, NV | D159: Ayala Landscaping | E159: CUSTOMER | F159: 08/02/2023 | G159: 45169
... A231: B5Y211533 | B231: S70 T4 V2 | C231: REVETHI DEALERS PVT LTD-C11838-BC, KOLKATA, WEST BENGAL | D231: UTKAL PROJECTS PVT.LTD. | E231: CUSTOMER | F231: 08/09/2023 | G231: 45169
A232: B5Y211045 | B232: S70 T4 V2 | C232: Bobcat of the Rockies, Henderson, CO-00518, HENDERSON, CO | D232: Sunny Day Concrete LLC | E232: CUSTOMER | F232: 45196 | G232: 45199
A233: B5Y211047 | B233: S70 T4 V2 | C233: Tri-State Bobcat Inc, Burnsville, MN-09113, BURNSVILLE, MN | D233: 4 Seasons Lawn Care | E233: CUSTOMER | F233: 09/26/2023 | G233: 45199
A234: B5Y211072 | B234: S70 T4 V2 | C234: Bobcat of Springfield, MO, Springfield, MO-00248, SPRINGFIELD, MO | D234: JASON ELLINGSWORTH | E234: CUSTOMER | F234: 09/21/2023 | G234: 45199
A235: B5Y211159 | B235: S70 T4 V2 | C235: Bingham Equipment Co, Buckeye, AZ-01068, BUCKEYE, AZ | D235: Apache Equipment Corporation | E235: CUSTOMER | F235: 09/13/2023 | G235: 45199
A236: B5Y211161 | B236: S70 T4 V2 | C236: Bingham Equipment Co, Mesa, AZ-01056, MESA, AZ | D236: Summit Equipment & Tool Rentals | E236: CUSTOMER | F236: 08/31/2023 | G236: 45199
A237: B5Y211185 | B237: S70 T4 V2 | C237: Bingham Equipment Co, Mesa, AZ-01056, MESA, AZ | D237: EFFEM Corporation | E237: CUSTOMER | F237: 09/21/2023 | G237: 45199
A238: B5Y211194 | B238: S70 T4 V2 | C238: Bobcat of Janesville, Janesville, WI-05267, JANESVILLE, WI | D238: Elkcast Aluminum | E238: CUSTOMER | F238: 09/01/2023 | G238: 45199
A239: B5Y211195 | B239: S70 T4 V2 | C239: Bobcat of Parry Sound Ltd., Nobel, ON-01037, NOBEL, ON | D239: HLS Hard-Line Solutions Inc. | E239: CUSTOMER | F239: 09/19/2023 | G239: 45199
A240: B5Y211197 | B240: S70 T4 V2 | C240: Bingham Equipment Co, Mesa, AZ-01056, MESA, AZ | D240: EFFEM Corporation | E240: CUSTOMER | F240: 09/21/2023 | G240: 45199
A241: B5Y211202 | B241: S70 T4 V2 | C241: Bobcat of Syracuse, a Division of Upstate Equipment, Syracuse, NY-05110, EAST SYRACUSE, NY | D241: AJ&J of Amherst Inc | E241: CUSTOMER | F241: 09/29/2023 | G241: 45199
A242: B5Y211203 | B242: S70 T4 V2 | C242: Bobcat of the Rockies, Henderson, CO-00518, HENDERSON, CO | D242: HOME BUILDER SITE SERVICES | E242: CUSTOMER | F242: 08/30/2023 | G242: 45199
A243: B5Y211206 | B243: S70 T4 V2 | C243: Bobcat of Tazewell, North Tazewell, VA-07490, NORTH TAZEWELL, VA | D243: Austinville Limestone Co | E243: CUSTOMER | F243: 09/13/2023 | G243: 45199
A244: B5Y211207 | B244: S70 T4 V2 | C244: Bingham Equipment Co, Mesa, AZ-01056, MESA, AZ | D244: EFFEM Corporation | E244: CUSTOMER | F244: 09/21/2023 | G244: 45199
... A339: B5Y211701 | B339: S70 T4 V2 | C339: REVETHI DEALERS PVT LTD-C11838-BLC, KOLKATA, WEST BENGAL | D339: DURGAPUR ENGG CONSTRACTION | E339: CUSTOMER | F339: 09/16/2023 | G339: 45199
A340: B5Y211023 | B340: S70 T4 V2 | C340: Bobcat of Los Angeles., Cerritos, CA-06879, CERRITOS, CA | D340: ZR Equipment Rentals, LLC | E340: CUSTOMER | F340: 45226 | G340: 45230
A341: B5Y211043 | B341: S70 T4 V2 | C341: Bobcat of Vineland, Vineland, NJ-00686, VINELAND, NJ | D341: B & B Parking Inc. | E341: CUSTOMER | F341: 45229 | G341: 45230
A342: B5Y211046 | B342: S70 T4 V2 | C342: Bobcat of Calgary, Calgary, AB-07983, CALGARY, AB | D342: KIDCO | E342: CUSTOMER | F342: 10/30/2023 | G342: 45230
A343: B5Y211057 | B343: S70 T4 V2 | C343: Flagstaff Equipment Co Inc, Flagstaff, AZ-03350, FLAGSTAFF, AZ | D343: Phillip Aerts | E343: CUSTOMER | F343: 10/05/2023 | G343: 45230
A344: B5Y211082 | B344: S70 T4 V2 | C344: K.C. Bobcat, Olathe, KS-05287, OLATHE, KS | D344: Tompkins Agricultural Industries LLC | E344: CUSTOMER | F344: 10/20/2023 | G344: 45230
A345: B5Y211122 | B345: S70 T4 V2 | C345: Bobcat of Los Angeles., Cerritos, CA-06879, CERRITOS, CA | D345: HRL INC, DBA HD EQUIPMENT | E345: CUSTOMER | F345: 10/12/2023 | G345: 45230
A346: B5Y211127 | B346: S70 T4 V2 | C346: Bobcat of Salem, Salem, OR-02108, SALEM, OR | D346: CHARLENE ROBERTS | E346: CUSTOMER | F346: 10/18/2023 | G346: 45230
A347: B5Y211145 | B347: S70 T4 V2 | C347: Bobcat of Los Angeles., Cerritos, CA-06879, CERRITOS, CA | D347: ZR Equipment Rentals, LLC | E347: CUSTOMER | F347: 10/27/2023 | G347: 45230
A348: B5Y211157 | B348: S70 T4 V2 | C348: Bobcat of Longview, Longview, TX-00615, LONGVIEW, TX | D348: Georgia_Pacific Wood Products LLC | E348: CUSTOMER | F348: 10/06/2023 | G348: 45230
...

Sheet Sheet2
A1: Delaer Name | B1: City | C1: Countr
A2: Miramar Bobcat, San Diego, CA-06877, SAN DIEGO, CA | B2: #VALUE! | C2: #VALUE!
A3: SUNBELT RENTALS - PC0133-N000300, Decatur, AL | B3: #VALUE! | C3: #VALUE!
A4: South Coast Bobcat, Orange, CA-08461, ORANGE, CA | B4: #VALUE! | C4: #VALUE!
A5: Valley Bobcat, Sun Valley, CA-09467, SUN VALLEY, CA | B5: SUN VALLEY | C5: #VALUE!
A6: Inland Bobcat, Riverside, CA-03080, RIVERSIDE, CA | B6: #VALUE! | C6: #VALUE!
A7: Valley Bobcat, Sun Valley, CA-09467, SUN VALLEY, CA | B7: SUN VALLEY | C7: #VALUE!
A8: Bobcat of the Rockies, Colorado Springs, CO-00528, COLORADO SPRINGS, CO | B8: #VALUE! | C8: #VALUE!
A9: Bobcat of the Rockies, Colorado Springs, CO-00528, COLORADO SPRINGS, CO | B9: #VALUE! | C9: #VALUE!
A10: Berchtold Equipment Co, Bakersfield, CA-00927, BAKERSFIELD, CA | B10: #VALUE! | C10: #VALUE!
A11: Bobcat of Ventura, Ventura, CA-08744, VENTURA, CA | B11: #VALUE! | C11: #VALUE!
A12: Bobcat of Eugene, Eugene, OR-07130, EUGENE, OR | B12: #VALUE! | C12: #VALUE!
A13: Bobcat of Gilroy, Gilroy, CA-02814, GILROY, CA | B13: #VALUE! | C13: #VALUE!
A14: Bobcat of Las Vegas, North Las Vegas, NV-01127, NORTH LAS VEGAS, NV | B14: #VALUE! | C14: #VALUE!
A15: Bobcat of Las Vegas, North Las Vegas, NV-01127, NORTH LAS VEGAS, NV | B15: #VALUE! | C15: #VALUE!
A16: Bobcat of Houston, Houston, TX-00521, HOUSTON, TX | B16: #VALUE! | C16: #VALUE!
A17: South Coast Bobcat, Orange, CA-08461, ORANGE, CA | B17: #VALUE! | C17: #VALUE!
A18: Bobcat of Houston, Houston, TX-00521, HOUSTON, TX | B18: #VALUE! | C18: #VALUE!
A19: Bingham Equipment Co, Tucson, AZ-01075, TUCSON, AZ | B19: #VALUE! | C19: #VALUE!
... A29: Gage County Equipment Inc, Beatrice, NE-03536, BEATRICE, NE | B29: #VALUE! | C29: #VALUE!
A30: Bobcat of the Rockies, Parker, CO-00527, PARKER, CO | B30: PARKER | C30: #VALUE!
A31: Bingham Equipment Co, Mesa, AZ-01056, MESA, AZ | B31: #VALUE! | C31: #VALUE!
A32: Bingham Equipment Co, Tucson, AZ-01075, TUCSON, AZ | B32: #VALUE! | C32: #VALUE!
A33: Bobcat of Phoenix, Phoenix, AZ-01055, PHOENIX, AZ | B33: #VALUE! | C33: #VALUE!
A34: Bobcat of Phoenix, Phoenix, AZ-01055, PHOENIX, AZ | B34: #VALUE! | C34: #VALUE!
A35: Bobcat of Albuquerque, Albuquerque, NM-00574, ALBUQUERQUE, NM | B35: #VALUE! | C35: #VALUE!
A36: Bobcat of Albuquerque, Albuquerque, NM-00574, ALBUQUERQUE, NM | B36: #VALUE! | C36: #VALUE!
A37: Bobcat of Fresno, Fresno, CA-01119, FRESNO, CA | B37: #VALUE! | C37: #VALUE!
A38: K.C. Bobcat, Olathe, KS-05287, OLATHE, KS | B38: #VALUE! | C38: #VALUE!
A39: Bobcat of San Antonio, San Antonio, TX-07742, SAN ANTONIO, TX | B39: #VALUE! | C39: #VALUE!
A40: Bobcat of Motor City East, Chesterfield, MI-01035, CHESTERFIELD, MI | B40: CHESTERFIELD | C40: #VALUE!
A41: Bobcat of Reno, Reno, NV-01933, SPARKS, NV | B41: #VALUE! | C41: #VALUE!
A42: K.C. Bobcat, Olathe, KS-05287, OLATHE, KS | B42: #VALUE! | C42: #VALUE!
A43: Bobcat of Las Vegas, North Las Vegas, NV-01127, NORTH LAS VEGAS, NV | B43: #VALUE! | C43: #VALUE!
A44: Bobcat of Houston, Baytown, TX-09685, BAYTOWN, TX | B44: #VALUE! | C44: #VALUE!
A45: Bingham Equipment Co, Mesa, AZ-01056, MESA, AZ | B45: #VALUE! | C45: #VALUE!
A46: Bobcat of Albuquerque, Albuquerque, NM-00574, ALBUQUERQUE, NM | B46: #VALUE! | C46: #VALUE!
A47: Bobcat of Phoenix, Phoenix, AZ-01055, PHOENIX, AZ | B47: #VALUE! | C47: #VALUE!
A48: Bobcat of Las Vegas, North Las Vegas, NV-01127, NORTH LAS VEGAS, NV | B48: #VALUE! | C48: #VALUE!
A49: Bobcat of Gilroy, Gilroy, CA-02814, GILROY, CA | B49: #VALUE! | C49: #VALUE!
A50: Bobcat of Las Vegas, North Las Vegas, NV-01127, NORTH LAS VEGAS, NV | B50: #VALUE! | C50: #VALUE!
A51: Bobcat of Las Vegas, North Las Vegas, NV-01127, NORTH LAS VEGAS, NV | B51: #VALUE! | C51: #VALUE!
A52: Bobcat of New York City, Maspeth, NY-08828, MASPETH, NY | B52: #VALUE! | C52: #VALUE!
... A165: South Coast Bobcat, Orange, CA-08461, ORANGE, CA | B165: #VALUE! | C165: #VALUE!
A166: Valley Bobcat, Sun Valley, CA-09467, SUN VALLEY, CA | B166: SUN VALLEY | C166: #VALUE!
A167: Valley Bobcat, Sun Valley, CA-09467, SUN VALLEY, CA | B167: SUN VALLEY | C167: #VALUE!
A168: Bingham Equipment Co, Buckeye, AZ-01068, BUCKEYE, AZ | B168: #VALUE! | C168: #VALUE!
A169: Bingham Equipment Co, Buckeye, AZ-01068, BUCKEYE, AZ | B169: #VALUE! | C169: #VALUE!
A170: Bobcat of Phoenix, Phoenix, AZ-01055, PHOENIX, AZ | B170: #VALUE! | C170: #VALUE!
A171: Inland Bobcat, Riverside, CA-03080, RIVERSIDE, CA | B171: #VALUE! | C171: #VALUE!
A172: Bingham Equipment Co, Mesa, AZ-01056, MESA, AZ | B172: #VALUE! | C172: #VALUE!
A173: Bingham Equipment Co, Buckeye, AZ-01068, BUCKEYE, AZ | B173: #VALUE! | C173: #VALUE!
A174: Bingham Equipment Co, Buckeye, AZ-01068, BUCKEYE, AZ | B174: #VALUE! | C174: #VALUE!
A175: Bingham Equipment Co, Mesa, AZ-01056, MESA, AZ | B175: #VALUE! | C175: #VALUE!
A176: Bobcat of North Jersey, Totowa, NJ-07333, TOTOWA, NJ | B176: #VALUE! | C176: #VALUE!
A177: Bobcat of Syracuse, a Division of Upstate Equipment, Syracuse, NY-05110, EAST SYRACUSE, NY | B177: #VALUE! | C177: #VALUE!
A178: Bobcat of the Rockies, Windsor, CO-00524, WINDSOR, CO | B178: #VALUE! | C178: #VALUE!
A179: Bobcat of the Rockies, Henderson, CO-00518, HENDERSON, CO | B179: #VALUE! | C179: #VALUE!
... A203: Bobcat of Las Vegas, North Las Vegas, NV-01127, NORTH LAS VEGAS, NV | B203: #VALUE! | C203: #VALUE!
A204: Valley Bobcat, Sun Valley, CA-09467, SUN VALLEY, CA | B204: SUN VALLEY | C204: #VALUE!
A205: Bobcat of Ventura, Ventura, CA-08744, VENTURA, CA | B205: #VALUE! | C205: #VALUE!
A206: Bobcat of Las Vegas, North Las Vegas, NV-01127, NORTH LAS VEGAS, NV | B206: #VALUE! | C206: #VALUE!
A207: Pfeifer Implement Co, Sioux Falls, SD-07522, SIOUX FALLS, SD | B207: #VALUE! | C207: #VALUE!
A208: Bobcat of Mason City, Mason City, IA-08921, MASON CITY, IA | B208: #VALUE! | C208: #VALUE!
A209: Bobcat of Chico, Chico, CA-02394, CHICO, CA | B209: #VALUE! | C209: #VALUE!
A210: Bobcat of Miami, Hialeah Gardens, FL-03010, DORAL, FL | B210: #VALUE! | C210: #VALUE!
A211: Bobcat Central, Inc., Merced, CA-00626, MERCED, CA | B211: #VALUE! | C211: #VALUE!
A212: Bobcat of Fremont, Fremont, CA-05319, FREMONT, CA | B212: #VALUE! | C212: #VALUE!
A213: SUNBELT RENTALS - PC0213-N001102, Cincinnati, OH | B213: #VALUE! | C213: #VALUE!
A214: Bobcat of Chadron, Chadron, NE-01932, CHADRON, NE | B214: #VALUE! | C214: #VALUE!
A215: Atlas Bobcat, Elk Grove Village, IL-00450, ELK GROVE VILLAGE, IL | B215: #VALUE! | C215: #VALUE!
A216: Bobcat of Miami, Hialeah Gardens, FL-03010, DORAL, FL | B216: #VALUE! | C216: #VALUE!
... A370: Bobcat of Toronto, Brampton, ON-04316, BRAMPTON, ON | B370: #VALUE! | C370: #VALUE!
A371: Valley Bobcat, Sun Valley, CA-09467, SUN VALLEY, CA | B371: SUN VALLEY | C371: #VALUE!
A372: Valley Bobcat, Sun Valley, CA-09467, SUN VALLEY, CA | B372: SUN VALLEY | C372: #VALUE!
A373: Gage County Equipment Inc, Beatrice, NE-03536, BEATRICE, NE | B373: #VALUE! | C373: #VALUE!
A374: Bobcat of Los Angeles., Cerritos, CA-06879, CERRITOS, CA | B374: #VALUE! | C374: #VALUE!
A375: Bobcat of Phoenix, Phoenix, AZ-01055, PHOENIX, AZ | B375: #VALUE! | C375: #VALUE!
A376: Bobcat of Phoenix, Phoenix, AZ-01055, PHOENIX, AZ | B376: #VALUE! | C376: #VALUE!
A377: Bobcat of Calgary, Calgary, AB-07983, CALGARY, AB | B377: #VALUE! | C377: #VALUE!
A378: Bobcat of the Rockies, Henderson, CO-00518, HENDERSON, CO | B378: #VALUE! | C378: #VALUE!
A379: Bobcat of the Finger Lakes, Fairport, NY-02412, FAIRPORT, NY | B379: #VALUE! | C379: #VALUE!
A380: Inland Bobcat, Riverside, CA-03080, RIVERSIDE, CA | B380: #VALUE! | C380: #VALUE!
A381: Inland Bobcat, Riverside, CA-03080, RIVERSIDE, CA | B381: #VALUE! | C381: #VALUE!
A382: Bobcat of Los Angeles., Cerritos, CA-06879, CERRITOS, CA | B382: #VALUE! | C382: #VALUE!
A383: Bobcat of Los Angeles., Cerritos, CA-06879, CERRITOS, CA | B383: #VALUE! | C383: #VALUE!
A384: Miramar Bobcat, San Diego, CA-06877, SAN DIEGO, CA | B384: #VALUE! | C384: #VALUE!
A385: Valley Bobcat, Sun Valley, CA-09467, SUN VALLEY, CA | B385: SUN VALLEY | C385: #VALUE!
A386: Capital City Equipment Company, Des Moines, IA-01565, DES MOINES, IA | B386: #VALUE! | C386: #VALUE!
A387: Metro Bobcat, Inc., White Marsh, MD-07128, WHITE MARSH, MD | B387: #VALUE! | C387: #VALUE!
A388: Inland Bobcat, Riverside, CA-03080, RIVERSIDE, CA | B388: #VALUE! | C388: #VALUE!
A389: Bingham Equipment Co, Mesa, AZ-01056, MESA, AZ | B389: #VALUE! | C389: #VALUE!
A390: SUNBELT RENTALS - PC0568-N100793, Rochester, MN | B390: #VALUE! | C390: #VALUE!
A391: Loader Services & Equipment, Inc., Pelham, AL-05425, PELHAM, AL | B391: #VALUE! | C391: #VALUE!
A392: Atlas Bobcat, Mokena, IL-00275, MOKENA, IL | B392: #VALUE! | C392: #VALUE!
A393: Valley Bobcat, Sun Valley, CA-09467, SUN VALLEY, CA | B393: SUN VALLEY | C393: #VALUE!
A394: SUNBELT RENTALS - PC7025-N103602, Brantford, ON | B394: #VALUE! | C394: #VALUE!
A395: SUNBELT RENTALS - PC0123 (NO DOCK)-N0000123, Pinellas Park, FL | B395: #VALUE! | C395: #VALUE!
A396: SUNBELT RENTALS - PC1280-N107007, Fort Smith, AR | B396: #VALUE! | C396: #VALUE!
A397: Intermountain Bobcat - Salt Lake, West Valley City, UT-08352, WEST VALLEY CITY, UT | B397: #VALUE! | C397: #VALUE!
...

Sheet Rough
A1: Serial Number | B1: Model | C1: Dealer Name | D1: City | E1: Country/region | F1: Customer Name | G1: Customer Type | H1: Reported Stolen | I1: Reported Stolen Date | J1: Date of Delivery | K1: Download Date | L1: Salesperson
A2: B5Y211008 | B2: S70 T4 V2 | C2: Miramar Bobcat, San Diego, CA-06877, SAN DIEGO, CA | D2: #VALUE! | E2: #VALUE! | F2: HERNANDEZ BROTHERS LANDSCAPING | G2: CUSTOMER | J2: 45070 | K2: 45077 | L2: Matthew Jarvis
A3: B5Y211013 | B3: S70 T4 V2 | C3: SUNBELT RENTALS - PC0133-N000300, Decatur, AL | D3: #VALUE! | E3: #VALUE! | F3: SUNBELT RENTALS - PC0133-N000300, Decatur, AL | G3: NATIONALACCOUNT | J3: 45061 | K3: 45077
A4: B5Y211015 | B4: S70 T4 V2 | C4: South Coast Bobcat, Orange, CA-08461, ORANGE, CA | D4: #VALUE! | E4: #VALUE! | F4: Instant Hauling | G4: CUSTOMER | J4: 45071 | K4: 45077 | L4: Dan Arevalo
A5: B5Y211028 | B5: S70 T4 V2 | C5: Valley Bobcat, Sun Valley, CA-09467, SUN VALLEY, CA | D5: SUN VALLEY | E5: #VALUE! | F5: Charlie & Sons Trucking | G5: CUSTOMER | J5: 45070 | K5: 45077 | L5: Jonpierre Rejas
A6: B5Y211031 | B6: S70 T4 V2 | C6: Inland Bobcat, Riverside, CA-03080, RIVERSIDE, CA | D6: #VALUE! | E6: #VALUE! | F6: Ready Equipment Rental | G6: CUSTOMER | J6: 45063 | K6: 45077 | L6: Hector Sanchez
A7: B5Y211032 | B7: S70 T4 V2 | C7: Valley Bobcat, Sun Valley, CA-09467, SUN VALLEY, CA | D7: SUN VALLEY | E7: #VALUE! | F7: Server Construction, Inc. | G7: CUSTOMER | J7: 45069 | K7: 45077 | L7: Jonpierre Rejas
A8: B5Y211036 | B8: S70 T4 V2 | C8: Bobcat of the Rockies, Colorado Springs, CO-00528, COLORADO SPRINGS, CO | D8: #VALUE! | E8: #VALUE! | F8: BILLS TOOL RENTAL | G8: CUSTOMER | J8: 45071 | K8: 45077 | L8: Daniel Hankins
A9: B5Y211065 | B9: S70 T4 V2 | C9: Bobcat of the Rockies, Colorado Springs, CO-00528, COLORADO SPRINGS, CO | D9: #VALUE! | E9: #VALUE! | F9: BILLS TOOL RENTAL | G9: CUSTOMER | J9: 45071 | K9: 45077 | L9: Daniel Hankins
A10: B5Y211067 | B10: S70 T4 V2 | C10: Berchtold Equipment Co, Bakersfield, CA-00927, BAKERSFIELD, CA | D10: #VALUE! | E10: #VALUE! | F10: DO IT BEST - 6089-N106960, Rosamond, CA | G10: NATIONALACCOUNT | J10: 45064 | K10: 45077 | L10: Terry Spencer
A11: B5Y211085 | B11: S70 T4 V2 | C11: Bobcat of Ventura, Ventura, CA-08744, VENTURA, CA | D11: #VALUE! | E11: #VALUE! | F11: Antonio Benitez Landscape | G11: CUSTOMER | J11: 45071 | K11: 45077 | L11: Randy Dvorak
A12: B5Y211100 | B12: S70 T4 V2 | C12: Bobcat of Eugene, Eugene, OR-07130, EUGENE, OR | D12: #VALUE! | E12: #VALUE! | F12: Zoltan Molar | G12: CUSTOMER | J12: 45066 | K12: 45077 | L12: Brandon Weaver
A13: B5Y211104 | B13: S70 T4 V2 | C13: Bobcat of Gilroy, Gilroy, CA-02814, GILROY, CA | D13: #VALUE! | E13: #VALUE! | F13: Quynh Ngo | G13: CUSTOMER | J13: 45069 | K13: 45077 | L13: Alex Serdiuk
A14: B5Y211007 | B14: S70 T4 V2 | C14: Bobcat of Las Vegas, North Las Vegas, NV-01127, NORTH LAS VEGAS, NV | D14: #VALUE! | E14: #VALUE! | F14: Medel Repairs LLC. | G14: CUSTOMER | J14: 45091 | K14: 45104 | L14: Carlo Damelio
A15: B5Y211010 | B15: S70 T4 V2 | C15: Bobcat of Las Vegas, North Las Vegas, NV-01127, NORTH LAS VEGAS, NV | D15: #VALUE! | E15: #VALUE! | F15: GREENSCAPES OF NEVADA LLC. | G15: CUSTOMER | J15: 45093 | K15: 45104 | L15: Carlo Damelio
A16: B5Y211011 | B16: S70 T4 V2 | C16: Bobcat of Houston, Houston, TX-00521, HOUSTON, TX | D16: #VALUE! | E16: #VALUE! | F16: INDUSTRIAL TX CORP | G16: CUSTOMER | J16: 45076 | K16: 45104 | L16: Daniel von Gontard
A17: B5Y211012 | B17: S70 T4 V2 | C17: South Coast Bobcat, Orange, CA-08461, ORANGE, CA | D17: #VALUE! | E17: #VALUE! | F17: Munoz Hauling Inc. | G17: CUSTOMER | J17: 45092 | K17: 45104 | L17: Dan Arevalo
A18: B5Y211014 | B18: S70 T4 V2 | C18: Bobcat of Houston, Houston, TX-00521, HOUSTON, TX | D18: #VALUE! | E18: #VALUE! | F18: G.C. HOMES AND INVESTMENTS LLC | G18: CUSTOMER | J18: 45077 | K18: 45104 | L18: Josh Kimich
A19: B5Y211017 | B19: S70 T4 V2 | C19: Bingham Equipment Co, Tucson, AZ-01075, TUCSON, AZ | D19: #VALUE! | E19: #VALUE! | F19: Southwest Equipment LLC | G19: CUSTOMER | J19: 45073 | K19: 45104 | L19: Victor Lopez
... A29: B5Y211041 | B29: S70 T4 V2 | C29: Gage County Equipment Inc, Beatrice, NE-03536, BEATRICE, NE | D29: #VALUE! | E29: #VALUE! | F29: Eric Engelman | G29: CUSTOMER | J29: 45093 | K29: 45104 | L29: Dale Zimmerman
A30: B5Y211053 | B30: S70 T4 V2 | C30: Bobcat of the Rockies, Parker, CO-00527, PARKER, CO | D30: PARKER | E30: #VALUE! | F30: KELLEY SPRINKLER AND LANDSCAPE | G30: CUSTOMER | J30: 45092 | K30: 45104 | L30: Rollie McDaniel
A31: B5Y211060 | B31: S70 T4 V2 | C31: Bingham Equipment Co, Mesa, AZ-01056, MESA, AZ | D31: #VALUE! | E31: #VALUE! | F31: Teresa Bautista | G31: CUSTOMER | J31: 45076 | K31: 45104 | L31: Brandon Townsend
A32: B5Y211062 | B32: S70 T4 V2 | C32: Bingham Equipment Co, Tucson, AZ-01075, TUCSON, AZ | D32: #VALUE! | E32: #VALUE! | F32: LANDSCAPE SOLUTIONS | G32: CUSTOMER | J32: 45079 | K32: 45104 | L32: Victor Lopez
A33: B5Y211064 | B33: S70 T4 V2 | C33: Bobcat of Phoenix, Phoenix, AZ-01055, PHOENIX, AZ | D33: #VALUE! | E33: #VALUE! | F33: MasterAZscapes LLC | G33: CUSTOMER | J33: 45089 | K33: 45104 | L33: Gary Walker
A34: B5Y211068 | B34: S70 T4 V2 | C34: Bobcat of Phoenix, Phoenix, AZ-01055, PHOENIX, AZ | D34: #VALUE! | E34: #VALUE! | F34: MasterAZscapes LLC | G34: CUSTOMER | J34: 45089 | K34: 45104 | L34: Gary Walker
A35: B5Y211069 | B35: S70 T4 V2 | C35: Bobcat of Albuquerque, Albuquerque, NM-00574, ALBUQUERQUE, NM | D35: #VALUE! | E35: #VALUE! | F35: RAC Construction, INC. | G35: CUSTOMER | J35: 45086 | K35: 45104 | L35: Miguel Merino
A36: B5Y211070 | B36: S70 T4 V2 | C36: Bobcat of Albuquerque, Albuquerque, NM-00574, ALBUQUERQUE, NM | D36: #VALUE! | E36: #VALUE! | F36: FRANKS SUPPLY CO | G36: CUSTOMER | J36: 45071 | K36: 45104 | L36: Miguel Merino
A37: B5Y211074 | B37: S70 T4 V2 | C37: Bobcat of Fresno, Fresno, CA-01119, FRESNO, CA | D37: #VALUE! | E37: #VALUE! | F37: SALAS CONCRETE | G37: CUSTOMER | J37: 45072 | K37: 45104 | L37: Ryan Wilson
A38: B5Y211077 | B38: S70 T4 V2 | C38: K.C. Bobcat, Olathe, KS-05287, OLATHE, KS | D38: #VALUE! | E38: #VALUE! | F38: The Monarch Cement Company | G38: CUSTOMER | J38: 45076 | K38: 45104 | L38: Derek Diederich
A39: B5Y211080 | B39: S70 T4 V2 | C39: Bobcat of San Antonio, San Antonio, TX-07742, SAN ANTONIO, TX | D39: #VALUE! | E39: #VALUE! | F39: WATSONSUPERSTORE OF SAN ANTONIO INC. | G39: CUSTOMER | J39: 45089 | K39: 45104 | L39: Eli Esquivel
A40: B5Y211083 | B40: S70 T4 V2 | C40: Bobcat of Motor City East, Chesterfield, MI-01035, CHESTERFIELD, MI | D40: CHESTERFIELD | E40: #VALUE! | F40: Max Demolition | G40: CUSTOMER | J40: 45079 | K40: 45104 | L40: Ray Henwood
A41: B5Y211084 | B41: S70 T4 V2 | C41: Bobcat of Reno, Reno, NV-01933, SPARKS, NV | D41: #VALUE! | E41: #VALUE! | F41: QUALITY INYO CONCRETE | G41: CUSTOMER | J41: 45097 | K41: 45104 | L41: Karl Tremblay
A42: B5Y211087 | B42: S70 T4 V2 | C42: K.C. Bobcat, Olathe, KS-05287, OLATHE, KS | D42: #VALUE! | E42: #VALUE! | F42: The Monarch Cement Company | G42: CUSTOMER | J42: 45076 | K42: 45104 | L42: Derek Diederich
A43: B5Y211092 | B43: S70 T4 V2 | C43: Bobcat of Las Vegas, North Las Vegas, NV-01127, NORTH LAS VEGAS, NV | D43: #VALUE! | E43: #VALUE! | F43: ALPHA LANDSCAPES | G43: CUSTOMER | J43: 45096 | K43: 45104 | L43: Carlo Damelio
A44: B5Y211093 | B44: S70 T4 V2 | C44: Bobcat of Houston, Baytown, TX-09685, BAYTOWN, TX | D44: #VALUE! | E44: #VALUE! | F44: G.C. HOMES AND INVESTMENTS LLC | G44: CUSTOMER | J44: 45072 | K44: 45104 | L44: Josh Kimich
A45: B5Y211094 | B45: S70 T4 V2 | C45: Bingham Equipment Co, Mesa, AZ-01056, MESA, AZ | D45: #VALUE! | E45: #VALUE! | F45: GDL CONSTRUCTION PRO LLC | G45: CUSTOMER | J45: 45097 | K45: 45104 | L45: Ashley Ghose
A46: B5Y211095 | B46: S70 T4 V2 | C46: Bobcat of Albuquerque, Albuquerque, NM-00574, ALBUQUERQUE, NM | D46: #VALUE! | E46: #VALUE! | F46: RAC Construction, INC. | G46: CUSTOMER | J46: 45086 | K46: 45104 | L46: Miguel Merino
A47: B5Y211098 | B47: S70 T4 V2 | C47: Bobcat of Phoenix, Phoenix, AZ-01055, PHOENIX, AZ | D47: #VALUE! | E47: #VALUE! | F47: Home Builders Site Service AZ | G47: CUSTOMER | J47: 45090 | K47: 45104 | L47: Gary Walker
A48: B5Y211106 | B48: S70 T4 V2 | C48: Bobcat of Las Vegas, North Las Vegas, NV-01127, NORTH LAS VEGAS, NV | D48: #VALUE! | E48: #VALUE! | F48: ALPHA LANDSCAPES | G48: CUSTOMER | J48: 45096 | K48: 45104 | L48: Carlo Damelio
A49: B5Y211107 | B49: S70 T4 V2 | C49: Bobcat of Gilroy, Gilroy, CA-02814, GILROY, CA | D49: #VALUE! | E49: #VALUE! | F49: Quynh Ngo | G49: CUSTOMER | J49: 45097 | K49: 45104 | L49: Alex Serdiuk
A50: B5Y211108 | B50: S70 T4 V2 | C50: Bobcat of Las Vegas, North Las Vegas, NV-01127, NORTH LAS VEGAS, NV | D50: #VALUE! | E50: #VALUE! | F50: ALPHA LANDSCAPES | G50: CUSTOMER | J50: 45096 | K50: 45104 | L50: Carlo Damelio
A51: B5Y211111 | B51: S70 T4 V2 | C51: Bobcat of Las Vegas, North Las Vegas, NV-01127, NORTH LAS VEGAS, NV | D51: #VALUE! | E51: #VALUE! | F51: ALPHA LANDSCAPES | G51: CUSTOMER | J51: 45096 | K51: 45104 | L51: Carlo Damelio
A52: B5Y211116 | B52: S70 T4 V2 | C52: Bobcat of New York City, Maspeth, NY-08828, MASPETH, NY | D52: #VALUE! | E52: #VALUE! | F52: paul johnson custom bldg | G52: CUSTOMER | J52: 45093 | K52: 45104 | L52: Jim Badaracco
... A89: B5Y211369 | B89: S70 T4 V2 | C89: ASHA INFRACORE-C07923-BC, BANGALORE, KARNATAKA | D89: #VALUE! | E89: #VALUE! | F89: KIOCL LIMITED | G89: CUSTOMER | J89: 45103 | K89: 45107 | L89: Chetana Kalmane
A90: B5Y211006 | B90: S70 T4 V2 | C90: SUNSTATE EQUIPMENT - DNV-N002683, Commerce City, CO | D90: #VALUE! | E90: #VALUE! | F90: SUNSTATE EQUIPMENT - DNV-N002683, Commerce City, CO | G90: NATIONALACCOUNT | J90: 45134 | K90: 45138
A91: B5Y211039 | B91: S70 T4 V2 | C91: Bobcat of Calgary, Calgary, AB-07983, CALGARY, AB | D91: #VALUE! | E91: #VALUE! | F91: THE RENTAL GUYS.CA - CALGARY-N103500, Calgary, AB | G91: NATIONALACCOUNT | J91: 45125 | K91: 45138 | L91: Ashley Beames
A92: B5Y211042 | B92: S70 T4 V2 | C92: Sooland Bobcat, Sioux City, IA-02324, SIOUX CITY, IA | D92: #VALUE! | E92: #VALUE! | F92: Martin Diaz | G92: CUSTOMER | J92: 45113 | K92: 45138 | L92: Kevin Powell
A93: B5Y211052 | B93: S70 T4 V2 | C93: Bobcat of Toronto, Scarborough, ON-04218, SCARBOROUGH, ON | D93: #VALUE! | E93: #VALUE! | F93: Cooper Equipment Rentals Inc. | G93: CUSTOMER | J93: 45135 | K93: 45138 | L93: Kai Sorensen
A94: B5Y211059 | B94: S70 T4 V2 | C94: Bingham Equipment Co, Mesa, AZ-01056, MESA, AZ | D94: #VALUE! | E94: #VALUE! | F94: A to Z Equipment Rentals | G94: CUSTOMER | J94: 45105 | K94: 45138 | L94: Nate Stanton
A95: B5Y211071 | B95: S70 T4 V2 | C95: Bobcat of Houston/Pearland, Houston, TX-00553, HOUSTON, TX | D95: #VALUE! | E95: #VALUE! | F95: TNT TRACTOR RENTALS LLC | G95: CUSTOMER | J95: 45126 | K95: 45138 | L95: Josh Kimich
A96: B5Y211078 | B96: S70 T4 V2 | C96: Machineries Trakto, Laval, QC-00225, LAVAL, QC | D96: #VALUE! | E96: #VALUE! | F96: Delsan-Aim | G96: CUSTOMER | J96: 45111 | K96: 45138 | L96: Stevens Parker
A97: B5Y211081 | B97: S70 T4 V2 | C97: SUNSTATE EQUIPMENT - BWP-N95511, Baldwin Park, CA | D97: #VALUE! | E97: #VALUE! | F97: SUNSTATE EQUIPMENT - BWP-N95511, Baldwin Park, CA | G97: NATIONALACCOUNT | J97: 45078 | K97: 45138
A98: B5Y211090 | B98: S70 T4 V2 | C98: Bobcat of Contra Costa, Pittsburg, CA-01845, PITTSBURG, CA | D98: #VALUE! | E98: #VALUE! | F98: JAC CONSTRUCTION | G98: CUSTOMER | J98: 45121 | K98: 45138 | L98: Jay Alias
A99: B5Y211096 | B99: S70 T4 V2 | C99: Bobcat of Amarillo, Amarillo, TX-07302, AMARILLO, TX | D99: #VALUE! | E99: #VALUE! | F99: COLT MOLLOY | G99: CUSTOMER | J99: 45118 | K99: 45138 | L99: Rick Trejo
A100: B5Y211097 | B100: S70 T4 V2 | C100: SUNSTATE EQUIPMENT - BEN-N105256, Benicia, CA | D100: #VALUE! | E100: #VALUE! | F100: SUNSTATE EQUIPMENT - BEN-N105256, Benicia, CA | G100: NATIONALACCOUNT | J100: 45138 | K100: 45138 | L100: Warranty Admin
A101: B5Y211102 | B101: S70 T4 V2 | C101: SUNSTATE EQUIPMENT - BWP-N95511, Baldwin Park, CA | D101: #VALUE! | E101: #VALUE! | F101: SUNSTATE EQUIPMENT - BWP-N95511, Baldwin Park, CA | G101: NATIONALACCOUNT | J101: 45078 | K101: 45138
A102: B5Y211103 | B102: S70 T4 V2 | C102: SUNSTATE EQUIPMENT - PEO-N002423, Peoria, AZ | D102: #VALUE! | E102: #VALUE! | F102: SUNSTATE EQUIPMENT - PEO-N002423, Peoria, AZ | G102: NATIONALACCOUNT | J102: 45082 | K102: 45138
A103: B5Y211112 | B103: S70 T4 V2 | C103: Bobcat of Goleta, Goleta, CA-08743, GOLETA, CA | D103: #VALUE! | E103: #VALUE! | F103: Centerpoint | G103: CUSTOMER | J103: 45107 | K103: 45138 | L103: Jeff Wright
A104: B5Y211113 | B104: S70 T4 V2 | C104: SUNSTATE EQUIPMENT - DNV-N002683, Commerce City, CO | D104: #VALUE! | E104: #VALUE! | F104: SUNSTATE EQUIPMENT - DNV-N002683, Commerce City, CO | G104: NATIONALACCOUNT | J104: 45077 | K104: 45138
A105: B5Y211115 | B105: S70 T4 V2 | C105: Bobcat of El Paso, El Paso, TX-00573, EL PASO, TX | D105: #VALUE! | E105: #VALUE! | F105: Southwest Trucks and Equipment | G105: CUSTOMER | J105: 45086 | K105: 45138 | L105: James Napier
A106: B5Y211119 | B106: S70 T4 V2 | C106: Bobcat of Marble Falls, Marble Falls, TX-07305, Marble Falls, TX | D106: #VALUE! | E106: #VALUE! | F106: Casaperior, LLC. | G106: CUSTOMER | J106: 45120 | K106: 45138 | L106: Danny Lopez
A107: B5Y211128 | B107: S70 T4 V2 | C107: Bobcat of Salem, Salem, OR-02108, SALEM, OR | D107: #VALUE! | E107: #VALUE! | F107: Covanta-Marion County | G107: CUSTOMER | J107: 45114 | K107: 45138 | L107: Nathan Leao
A108: B5Y211131 | B108: S70 T4 V2 | C108: SUNSTATE EQUIPMENT - TUC-N002782, Tucson, AZ | D108: #VALUE! | E108: #VALUE! | F108: SUNSTATE EQUIPMENT - TUC-N002782, Tucson, AZ | G108: NATIONALACCOUNT | J108: 45082 | K108: 45138
A109: B5Y211133 | B109: S70 T4 V2 | C109: Bobcat of Sacramento, Sacramento, CA-01873, SACRAMENTO, CA | D109: #VALUE! | E109: #VALUE! | F109: MARTIN MARTINEZ PADILLA | G109: CUSTOMER | J109: 45128 | K109: 45138 | L109: Randy Erwin
A110: B5Y211135 | B110: S70 T4 V2 | C110: SUNSTATE EQUIPMENT - BWP-N95511, Baldwin Park, CA | D110: #VALUE! | E110: #VALUE! | F110: SUNSTATE EQUIPMENT - BWP-N95511, Baldwin Park, CA | G110: NATIONALACCOUNT | J110: 45078 | K110: 45138
A111: B5Y211137 | B111: S70 T4 V2 | C111: SUNSTATE EQUIPMENT - VEG-N002652, Henderson, NV | D111: #VALUE! | E111: #VALUE! | F111: SUNSTATE EQUIPMENT - VEG-N002652, Henderson, NV | G111: NATIONALACCOUNT | J111: 45083 | K111: 45138
A112: B5Y211141 | B112: S70 T4 V2 | C112: Inland Bobcat, Riverside, CA-03080, RIVERSIDE, CA | D112: #VALUE! | E112: #VALUE! | F112: JRC CONSTRUCTION | G112: CUSTOMER | J112: 45117 | K112: 45138 | L112: Art Mata
A113: B5Y211143 | B113: S70 T4 V2 | C113: Inland Bobcat, Riverside, CA-03080, RIVERSIDE, CA | D113: #VALUE! | E113: #VALUE! | F113: RUBEN FUNES | G113: CUSTOMER | J113: 45117 | K113: 45138 | L113: Art Mata
A114: B5Y211144 | B114: S70 T4 V2 | C114: Bingham Equipment Co, Mesa, AZ-01056, MESA, AZ | D114: #VALUE! | E114: #VALUE! | F114: Creative Landscape Images, LLC | G114: CUSTOMER | J114: 45135 | K114: 45138 | L114: Nate Stanton
A115: B5Y211146 | B115: S70 T4 V2 | C115: Bobcat of Houston, Houston, TX-00521, HOUSTON, TX | D115: #VALUE! | E115: #VALUE! | F115: TNT TRACTOR RENTALS LLC | G115: CUSTOMER | J115: 45126 | K115: 45138 | L115: Josh Kimich
A116: B5Y211149 | B116: S70 T4 V2 | C116: Bingham Equipment Co, Mesa, AZ-01056, MESA, AZ | D116: #VALUE! | E116: #VALUE! | F116: CREATIVE DESIGN LANDSCAPE | G116: CUSTOMER | J116: 45128 | K116: 45138 | L116: Nate Stanton
A117: B5Y211151 | B117: S70 T4 V2 | C117: Bingham Equipment Co, Mesa, AZ-01056, MESA, AZ | D117: #VALUE! | E117: #VALUE! | F117: CREATIVE DESIGN LANDSCAPE | G117: CUSTOMER | J117: 45128 | K117: 45138 | L117: Nate Stanton
A118: B5Y211152 | B118: S70 T4 V2 | C118: Bingham Equipment Co, Mesa, AZ-01056, MESA, AZ | D118: #VALUE! | E118: #VALUE! | F118: A to Z Equipment Rentals | G118: CUSTOMER | J118: 45105 | K118: 45138 | L118: Nate Stanton
A119: B5Y211155 | B119: S70 T4 V2 | C119: Bobcat of Phoenix, Phoenix, AZ-01055, PHOENIX, AZ | D119: #VALUE! | E119: #VALUE! | F119: Topos Construction And Landscaping LLC | G119: CUSTOMER | J119: 45125 | K119: 45138 | L119: Daniel Hernandez
A120: B5Y211156 | B120: S70 T4 V2 | C120: Bobcat of Phoenix, Phoenix, AZ-01055, PHOENIX, AZ | D120: #VALUE! | E120: #VALUE! | F120: LL & G LLC | G120: CUSTOMER | J120: 45125 | K120: 45138 | L120: Gary Walker
A121: B5Y211158 | B121: S70 T4 V2 | C121: Bingham Equipment Co, Mesa, AZ-01056, MESA, AZ | D121: #VALUE! | E121: #VALUE! | F121: A to Z Equipment Rentals | G121: CUSTOMER | J121: 45105 | K121: 45138 | L121: Nate Stanton
A122: B5Y211160 | B122: S70 T4 V2 | C122: Bobcat of Phoenix, Phoenix, AZ-01055, PHOENIX, AZ | D122: #VALUE! | E122: #VALUE! | F122: Deer Valley Pavers LLC | G122: CUSTOMER | J122: 45114 | K122: 45138 | L122: Gary Walker
A123: B5Y211163 | B123: S70 T4 V2 | C123: Bingham Equipment Co, Mesa, AZ-01056, MESA, AZ | D123: #VALUE! | E123: #VALUE! | F123: Unique Rock & Water, Inc. | G123: CUSTOMER | J123: 45131 | K123: 45138 | L123: Ashley Ghose
... A134: B5Y211196 | B134: S70 T4 V2 | C134: KARM SALES & SERVICE-C10750-BC, RAIPUR, CHHATTISGARH | D134: #VALUE! | E134: #VALUE! | F134: M/S SHAPOORJI PALLONJI | G134: CUSTOMER | J134: 45113 | K134: 45138 | L134: Altaf Khan
A135: B5Y211219 | B135: S70 T4 V2 | C135: SUNBELT RENTALS - PC0052-N000310, Spartanburg, SC | D135: #VALUE! | E135: #VALUE! | F135: SUNBELT RENTALS - PC0052-N000310, Spartanburg, SC | G135: NATIONALACCOUNT | J135: 45132 | K135: 45138
A136: B5Y211229 | B136: S70 T4 V2 | C136: Bobcat of North Texas - Fort Worth, Fort Worth, TX-00657, FORT WORTH, TX | D136: #VALUE! | E136: #VALUE! | F136: Taylor Rental Equipment | G136: CUSTOMER | J136: 45135 | K136: 45138 | L136: TRENT WALKER
A137: B5Y211244 | B137: S70 T4 V2 | C137: Inland Bobcat, Riverside, CA-03080, RIVERSIDE, CA | D137: #VALUE! | E137: #VALUE! | F137: Geovany Camacho | G137: CUSTOMER | J137: 45133 | K137: 45138 | L137: Art Mata
A138: B5Y211255 | B138: S70 T4 V2 | C138: SUNBELT RENTALS - PC1210-N106368, Warrendale, PA | D138: #VALUE! | E138: #VALUE! | F138: SUNBELT RENTALS - PC1210-N106368, Warrendale, PA | G138: NATIONALACCOUNT | J138: 45132 | K138: 45138
A139: B5Y211258 | B139: S70 T4 V2 | C139: SUNBELT RENTALS - PC0663-N102935, Bakersfield, CA | D139: #VALUE! | E139: #VALUE! | F139: SUNBELT RENTALS - PC0663-N102935, Bakersfield, CA | G139: NATIONALACCOUNT | J139: 45133 | K139: 45138
A140: B5Y211262 | B140: S70 T4 V2 | C140: SUNBELT RENTALS - PC0178-N000360, Hunt Valley, MD | D140: #VALUE! | E140: #VALUE! | F140: SUNBELT RENTALS - PC0178-N000360, Hunt Valley, MD | G140: NATIONALACCOUNT | J140: 45138 | K140: 45138
A141: B5Y211263 | B141: S70 T4 V2 | C141: SUNBELT RENTALS - PC1001-N103515, El Mirage, AZ | D141: #VALUE! | E141: #VALUE! | F141: SUNBELT RENTALS - PC1001-N103515, El Mirage, AZ | G141: NATIONALACCOUNT | J141: 45131 | K141: 45138
A142: B5Y211265 | B142: S70 T4 V2 | C142: SUNBELT RENTALS - PC0164-N000864, Swedesboro, NJ | D142: #VALUE! | E142: #VALUE! | F142: SUNBELT RENTALS - PC0164-N000864, Swedesboro, NJ | G142: NATIONALACCOUNT | J142: 45133 | K142: 45138
A143: B5Y211268 | B143: S70 T4 V2 | C143: Bingham Equipment Co, Mesa, AZ-01056, MESA, AZ | D143: #VALUE! | E143: #VALUE! | F143: EZEQUIEL HERNANDEZ | G143: CUSTOMER | J143: 45135 | K143: 45138 | L143: Ashley Ghose
A144: B5Y211274 | B144: S70 T4 V2 | C144: Bingham Equipment Co, Mesa, AZ-01056, MESA, AZ | D144: #VALUE! | E144: #VALUE! | F144: Arizona Yard Maintenance LLC | G144: CUSTOMER | J144: 45135 | K144: 45138 | L144: Brandon Townsend
A145: B5Y211455 | B145: S70 T4 V2 | C145: MARWELL COMPRESSORS AND EQQUIPMENTS INDIA PVT LTD-C02756-BLC, Coimbatore, Tamil Nadu | D145: #VALUE! | E145: #VALUE! | F145: SURYADEV ALLOYS AND POWER PVT LTD | G145: CUSTOMER | J145: 45127 | K145: 45138 | L145: BHL Purchase
A146: B5Y211034 | B146: S70 T4 V2 | C146: Bobcat of Lakeland, Lakeland, FL-08946, LAKELAND, FL | D146: #VALUE! | E146: #VALUE! | F146: RINKER MATERIALS | G146: CUSTOMER | J146: 08/21/2023 | K146: 45169
A147: B5Y211044 | B147: S70 T4 V2 | C147: Bobcat of West Chester, West Chester, PA-00280, WEST CHESTER, PA | D147: #VALUE! | E147: #VALUE! | F147: Rich Industrial Services Inc. | G147: CUSTOMER | J147: 08/09/2023 | K147: 45169
A148: B5Y211048 | B148: S70 T4 V2 | C148: Bobcat of Philadelphia, Warminster, PA-00965, WARMINSTER, PA | D148: #VALUE! | E148: #VALUE! | F148: Bello Brothers Construction | G148: CUSTOMER | J148: 07/26/2023 | K148: 45169
A149: B5Y211054 | B149: S70 T4 V2 | C149: UNITED RENTALS 801-N96333, Everett, MA | D149: #VALUE! | E149: #VALUE! | F149: UNITED RENTALS 801-N96333, Everett, MA | G149: NATIONALACCOUNT | J149: 08/08/2023 | K149: 45169
A150: B5Y211063 | B150: S70 T4 V2 | C150: Bobcat of San Antonio, San Antonio, TX-07742, SAN ANTONIO, TX | D150: #VALUE! | E150: #VALUE! | F150: Robles 1, LLC | G150: CUSTOMER | J150: 08/25/2023 | K150: 45169
A151: B5Y211099 | B151: S70 T4 V2 | C151: Miramar Bobcat, San Diego, CA-06877, SAN DIEGO, CA | D151: #VALUE! | E151: #VALUE! | F151: Alex Macias | G151: CUSTOMER | J151: 08/03/2023 | K151: 45169
A152: B5Y211126 | B152: S70 T4 V2 | C152: Bingham Equipment Co, Tucson, AZ-01075, TUCSON, AZ | D152: #VALUE! | E152: #VALUE! | F152: SANTA RITA LANDSCAPING | G152: CUSTOMER | J152: 07/31/2023 | K152: 45169
A153: B5Y211139 | B153: S70 T4 V2 | C153: Bobcat of Fresno, Fresno, CA-01119, FRESNO, CA | D153: #VALUE! | E153: #VALUE! | F153: SALAS CONCRETE | G153: CUSTOMER | J153: 08/24/2023 | K153: 45169
A154: B5Y211140 | B154: S70 T4 V2 | C154: Bobcat of Richmond, Ashland, VA-09758, ASHLAND, VA | D154: #VALUE! | E154: #VALUE! | F154: RENTAL STORES LLC | G154: CUSTOMER | J154: 08/09/2023 | K154: 45169
A155: B5Y211147 | B155: S70 T4 V2 | C155: Bobcat of Santa Rosa, Santa Rosa, CA-00632, SANTA ROSA, CA | D155: #VALUE! | E155: #VALUE! | F155: G Family Leasing LLC | G155: CUSTOMER | J155: 08/03/2023 | K155: 45169
...

Sheet Delaer Name_City
A1: Dealer Name | B1: City
A2: Miramar Bobcat, San Diego, CA-06877, SAN DIEGO, CA | B2: #VALUE!
A3: SUNBELT RENTALS - PC0133-N000300, Decatur, AL | B3: #VALUE!
A4: South Coast Bobcat, Orange, CA-08461, ORANGE, CA | B4: #VALUE!
A5: Valley Bobcat, Sun Valley, CA-09467, SUN VALLEY, CA | B5: SUN VALLEY
A6: Inland Bobcat, Riverside, CA-03080, RIVERSIDE, CA | B6: #VALUE!
A7: Valley Bobcat, Sun Valley, CA-09467, SUN VALLEY, CA | B7: SUN VALLEY
A8: Bobcat of the Rockies, Colorado Springs, CO-00528, COLORADO SPRINGS, CO | B8: #VALUE!
A9: Bobcat of the Rockies, Colorado Springs, CO-00528, COLORADO SPRINGS, CO | B9: #VALUE!
A10: Berchtold Equipment Co, Bakersfield, CA-00927, BAKERSFIELD, CA | B10: #VALUE!
A11: Bobcat of Ventura, Ventura, CA-08744, VENTURA, CA | B11: #VALUE!
A12: Bobcat of Eugene, Eugene, OR-07130, EUGENE, OR | B12: #VALUE!
A13: Bobcat of Gilroy, Gilroy, CA-02814, GILROY, CA | B13: #VALUE!
A14: Bobcat of Las Vegas, North Las Vegas, NV-01127, NORTH LAS VEGAS, NV | B14: #VALUE!
A15: Bobcat of Las Vegas, North Las Vegas, NV-01127, NORTH LAS VEGAS, NV | B15: #VALUE!
A16: Bobcat of Houston, Houston, TX-00521, HOUSTON, TX | B16: #VALUE!
A17: South Coast Bobcat, Orange, CA-08461, ORANGE, CA | B17: #VALUE!
A18: Bobcat of Houston, Houston, TX-00521, HOUSTON, TX | B18: #VALUE!
A19: Bingham Equipment Co, Tucson, AZ-01075, TUCSON, AZ | B19: #VALUE!
... A29: Gage County Equipment Inc, Beatrice, NE-03536, BEATRICE, NE | B29: #VALUE!
A30: Bobcat of the Rockies, Parker, CO-00527, PARKER, CO | B30: PARKER
A31: Bingham Equipment Co, Mesa, AZ-01056, MESA, AZ | B31: #VALUE!
A32: Bingham Equipment Co, Tucson, AZ-01075, TUCSON, AZ | B32: #VALUE!
A33: Bobcat of Phoenix, Phoenix, AZ-01055, PHOENIX, AZ | B33: #VALUE!
A34: Bobcat of Phoenix, Phoenix, AZ-01055, PHOENIX, AZ | B34: #VALUE!
A35: Bobcat of Albuquerque, Albuquerque, NM-00574, ALBUQUERQUE, NM | B35: #VALUE!
A36: Bobcat of Albuquerque, Albuquerque, NM-00574, ALBUQUERQUE, NM | B36: #VALUE!
A37: Bobcat of Fresno, Fresno, CA-01119, FRESNO, CA | B37: #VALUE!
A38: K.C. Bobcat, Olathe, KS-05287, OLATHE, KS | B38: #VALUE!
A39: Bobcat of San Antonio, San Antonio, TX-07742, SAN ANTONIO, TX | B39: #VALUE!
A40: Bobcat of Motor City East, Chesterfield, MI-01035, CHESTERFIELD, MI | B40: CHESTERFIELD
A41: Bobcat of Reno, Reno, NV-01933, SPARKS, NV | B41: #VALUE!
A42: K.C. Bobcat, Olathe, KS-05287, OLATHE, KS | B42: #VALUE!
A43: Bobcat of Las Vegas, North Las Vegas, NV-01127, NORTH LAS VEGAS, NV | B43: #VALUE!
A44: Bobcat of Houston, Baytown, TX-09685, BAYTOWN, TX | B44: #VALUE!
A45: Bingham Equipment Co, Mesa, AZ-01056, MESA, AZ | B45: #VALUE!
A46: Bobcat of Albuquerque, Albuquerque, NM-00574, ALBUQUERQUE, NM | B46: #VALUE!
A47: Bobcat of Phoenix, Phoenix, AZ-01055, PHOENIX, AZ | B47: #VALUE!
A48: Bobcat of Las Vegas, North Las Vegas, NV-01127, NORTH LAS VEGAS, NV | B48: #VALUE!
A49: Bobcat of Gilroy, Gilroy, CA-02814, GILROY, CA | B49: #VALUE!
A50: Bobcat of Las Vegas, North Las Vegas, NV-01127, NORTH LAS VEGAS, NV | B50: #VALUE!
A51: Bobcat of Las Vegas, North Las Vegas, NV-01127, NORTH LAS VEGAS, NV | B51: #VALUE!
A52: Bobcat of New York City, Maspeth, NY-08828, MASPETH, NY | B52: #VALUE!
... A165: South Coast Bobcat, Orange, CA-08461, ORANGE, CA | B165: #VALUE!
A166: Valley Bobcat, Sun Valley, CA-09467, SUN VALLEY, CA | B166: SUN VALLEY
A167: Valley Bobcat, Sun Valley, CA-09467, SUN VALLEY, CA | B167: SUN VALLEY
A168: Bingham Equipment Co, Buckeye, AZ-01068, BUCKEYE, AZ | B168: #VALUE!
A169: Bingham Equipment Co, Buckeye, AZ-01068, BUCKEYE, AZ | B169: #VALUE!
A170: Bobcat of Phoenix, Phoenix, AZ-01055, PHOENIX, AZ | B170: #VALUE!
A171: Inland Bobcat, Riverside, CA-03080, RIVERSIDE, CA | B171: #VALUE!
A172: Bingham Equipment Co, Mesa, AZ-01056, MESA, AZ | B172: #VALUE!
A173: Bingham Equipment Co, Buckeye, AZ-01068, BUCKEYE, AZ | B173: #VALUE!
A174: Bingham Equipment Co, Buckeye, AZ-01068, BUCKEYE, AZ | B174: #VALUE!
A175: Bingham Equipment Co, Mesa, AZ-01056, MESA, AZ | B175: #VALUE!
A176: Bobcat of North Jersey, Totowa, NJ-07333, TOTOWA, NJ | B176: #VALUE!
A177: Bobcat of Syracuse, a Division of Upstate Equipment, Syracuse, NY-05110, EAST SYRACUSE, NY | B177: #VALUE!
A178: Bobcat of the Rockies, Windsor, CO-00524, WINDSOR, CO | B178: #VALUE!
A179: Bobcat of the Rockies, Henderson, CO-00518, HENDERSON, CO | B179: #VALUE!
... A203: Bobcat of Las Vegas, North Las Vegas, NV-01127, NORTH LAS VEGAS, NV | B203: #VALUE!
A204: Valley Bobcat, Sun Valley, CA-09467, SUN VALLEY, CA | B204: SUN VALLEY
A205: Bobcat of Ventura, Ventura, CA-08744, VENTURA, CA | B205: #VALUE!
A206: Bobcat of Las Vegas, North Las Vegas, NV-01127, NORTH LAS VEGAS, NV | B206: #VALUE!
A207: Pfeifer Implement Co, Sioux Falls, SD-07522, SIOUX FALLS, SD | B207: #VALUE!
A208: Bobcat of Mason City, Mason City, IA-08921, MASON CITY, IA | B208: #VALUE!
A209: Bobcat of Chico, Chico, CA-02394, CHICO, CA | B209: #VALUE!
A210: Bobcat of Miami, Hialeah Gardens, FL-03010, DORAL, FL | B210: #VALUE!
A211: Bobcat Central, Inc., Merced, CA-00626, MERCED, CA | B211: #VALUE!
A212: Bobcat of Fremont, Fremont, CA-05319, FREMONT, CA | B212: #VALUE!
A213: SUNBELT RENTALS - PC0213-N001102, Cincinnati, OH | B213: #VALUE!
A214: Bobcat of Chadron, Chadron, NE-01932, CHADRON, NE | B214: #VALUE!
A215: Atlas Bobcat, Elk Grove Village, IL-00450, ELK GROVE VILLAGE, IL | B215: #VALUE!
A216: Bobcat of Miami, Hialeah Gardens, FL-03010, DORAL, FL | B216: #VALUE!
... A370: Bobcat of Toronto, Brampton, ON-04316, BRAMPTON, ON | B370: #VALUE!
A371: Valley Bobcat, Sun Valley, CA-09467, SUN VALLEY, CA | B371: SUN VALLEY
A372: Valley Bobcat, Sun Valley, CA-09467, SUN VALLEY, CA | B372: SUN VALLEY
A373: Gage County Equipment Inc, Beatrice, NE-03536, BEATRICE, NE | B373: #VALUE!
A374: Bobcat of Los Angeles., Cerritos, CA-06879, CERRITOS, CA | B374: #VALUE!
A375: Bobcat of Phoenix, Phoenix, AZ-01055, PHOENIX, AZ | B375: #VALUE!
A376: Bobcat of Phoenix, Phoenix, AZ-01055, PHOENIX, AZ | B376: #VALUE!
A377: Bobcat of Calgary, Calgary, AB-07983, CALGARY, AB | B377: #VALUE!
A378: Bobcat of the Rockies, Henderson, CO-00518, HENDERSON, CO | B378: #VALUE!
A379: Bobcat of the Finger Lakes, Fairport, NY-02412, FAIRPORT, NY | B379: #VALUE!
A380: Inland Bobcat, Riverside, CA-03080, RIVERSIDE, CA | B380: #VALUE!
A381: Inland Bobcat, Riverside, CA-03080, RIVERSIDE, CA | B381: #VALUE!
A382: Bobcat of Los Angeles., Cerritos, CA-06879, CERRITOS, CA | B382: #VALUE!
A383: Bobcat of Los Angeles., Cerritos, CA-06879, CERRITOS, CA | B383: #VALUE!
A384: Miramar Bobcat, San Diego, CA-06877, SAN DIEGO, CA | B384: #VALUE!
A385: Valley Bobcat, Sun Valley, CA-09467, SUN VALLEY, CA | B385: SUN VALLEY
A386: Capital City Equipment Company, Des Moines, IA-01565, DES MOINES, IA | B386: #VALUE!
A387: Metro Bobcat, Inc., White Marsh, MD-07128, WHITE MARSH, MD | B387: #VALUE!
A388: Inland Bobcat, Riverside, CA-03080, RIVERSIDE, CA | B388: #VALUE!
A389: Bingham Equipment Co, Mesa, AZ-01056, MESA, AZ | B389: #VALUE!
A390: SUNBELT RENTALS - PC0568-N100793, Rochester, MN | B390: #VALUE!
A391: Loader Services & Equipment, Inc., Pelham, AL-05425, PELHAM, AL | B391: #VALUE!
A392: Atlas Bobcat, Mokena, IL-00275, MOKENA, IL | B392: #VALUE!
A393: Valley Bobcat, Sun Valley, CA-09467, SUN VALLEY, CA | B393: SUN VALLEY
A394: SUNBELT RENTALS - PC7025-N103602, Brantford, ON | B394: #VALUE!
A395: SUNBELT RENTALS - PC0123 (NO DOCK)-N0000123, Pinellas Park, FL | B395: #VALUE!
A396: SUNBELT RENTALS - PC1280-N107007, Fort Smith, AR | B396: #VALUE!
A397: Intermountain Bobcat - Salt Lake, West Valley City, UT-08352, WEST VALLEY CITY, UT | B397: #VALUE!
...

Sheet Sheet0 (2)
A1: Serial Number | B1: Model | C1: Dealer Name | D1: Customer Name | E1: Customer Type | F1: Reported Stolen | G1: Reported Stolen Date | H1: Date of Delivery | I1: Machine Age | J1: Salesperson | L1: Machine Number
A2: B5Y211004 | B2: S70 T4 V2 | C2: Bingham Equipment Co, Mesa, AZ-01056, MESA, AZ | D2: A to Z Equipment Rentals | E2: CUSTOMER | H2: 06/20/2023 | I2: 24 | J2: Brandon Townsend | L2: =_xlfn.XLOOKUP(A2,S70Sheet!A:A,S70Sheet!A:A)
A3: B5Y211005 | B3: S70 T4 V2 | C3: Bingham Equipment Co, Mesa, AZ-01056, MESA, AZ | D3: A to Z Equipment Rentals | E3: CUSTOMER | H3: 06/20/2023 | I3: 24 | J3: Nate Stanton | L3: =_xlfn.XLOOKUP(A3,S70Sheet!A:A,S70Sheet!A:A)
A4: B5Y211006 | B4: S70 T4 V2 | C4: SUNSTATE EQUIPMENT - DNV-N002683, Commerce City, CO | D4: SUNSTATE EQUIPMENT - DNV-N002683, Commerce City, CO | E4: NATIONALACCOUNT | H4: 07/27/2023 | I4: 22 | L4: =_xlfn.XLOOKUP(A4,S70Sheet!A:A,S70Sheet!A:A)
A5: B5Y211007 | B5: S70 T4 V2 | C5: Bobcat of Las Vegas, North Las Vegas, NV-01127, NORTH LAS VEGAS, NV | D5: Medel Repairs LLC. | E5: CUSTOMER | H5: 06/14/2023 | I5: 24 | J5: Carlo Damelio | L5: =_xlfn.XLOOKUP(A5,S70Sheet!A:A,S70Sheet!A:A)
A6: B5Y211008 | B6: S70 T4 V2 | C6: Miramar Bobcat, San Diego, CA-06877, SAN DIEGO, CA | D6: HERNANDEZ BROTHERS LANDSCAPING | E6: CUSTOMER | H6: 05/24/2023 | I6: 24 | J6: Matthew Jarvis | L6: =_xlfn.XLOOKUP(A6,S70Sheet!A:A,S70Sheet!A:A)
A7: B5Y211009 | B7: S70 T4 V2 | C7: Bobcat of Las Vegas, North Las Vegas, NV-01127, NORTH LAS VEGAS, NV | D7: TORO CONSULTING | E7: CUSTOMER | H7: 06/28/2023 | I7: 24 | J7: Carlo Damelio | L7: =_xlfn.XLOOKUP(A7,S70Sheet!A:A,S70Sheet!A:A)
A8: B5Y211010 | B8: S70 T4 V2 | C8: Bobcat of Las Vegas, North Las Vegas, NV-01127, NORTH LAS VEGAS, NV | D8: GREENSCAPES OF NEVADA LLC. | E8: CUSTOMER | H8: 06/16/2023 | I8: 24 | J8: Carlo Damelio | L8: =_xlfn.XLOOKUP(A8,S70Sheet!A:A,S70Sheet!A:A)
A9: B5Y211011 | B9: S70 T4 V2 | C9: Bobcat of Houston, Houston, TX-00521, HOUSTON, TX | D9: INDUSTRIAL TX CORP | E9: CUSTOMER | H9: 05/30/2023 | I9: 24 | J9: Daniel von Gontard | L9: =_xlfn.XLOOKUP(A9,S70Sheet!A:A,S70Sheet!A:A)
A10: B5Y211012 | B10: S70 T4 V2 | C10: South Coast Bobcat, Orange, CA-08461, ORANGE, CA | D10: Munoz Hauling Inc. | E10: CUSTOMER | H10: 06/15/2023 | I10: 24 | J10: Dan Arevalo | L10: =_xlfn.XLOOKUP(A10,S70Sheet!A:A,S70Sheet!A:A)
A11: B5Y211013 | B11: S70 T4 V2 | C11: SUNBELT RENTALS - PC0133-N000300, Decatur, AL | D11: SUNBELT RENTALS - PC0133-N000300, Decatur, AL | E11: NATIONALACCOUNT | H11: 05/15/2023 | I11: 24 | L11: =_xlfn.XLOOKUP(A11,S70Sheet!A:A,S70Sheet!A:A)
A12: B5Y211014 | B12: S70 T4 V2 | C12: Bobcat of Houston, Houston, TX-00521, HOUSTON, TX | D12: G.C. HOMES AND INVESTMENTS LLC | E12: CUSTOMER | H12: 05/31/2023 | I12: 24 | J12: Josh Kimich | L12: =_xlfn.XLOOKUP(A12,S70Sheet!A:A,S70Sheet!A:A)
A13: B5Y211015 | B13: S70 T4 V2 | C13: South Coast Bobcat, Orange, CA-08461, ORANGE, CA | D13: Instant Hauling | E13: CUSTOMER | H13: 05/25/2023 | I13: 24 | J13: Dan Arevalo | L13: =_xlfn.XLOOKUP(A13,S70Sheet!A:A,S70Sheet!A:A)
A14: B5Y211016 | B14: S70 T4 V2 | C14: Bobcat of Las Vegas, North Las Vegas, NV-01127, NORTH LAS VEGAS, NV | D14: AZ LANDSCAPE & HAULING | E14: CUSTOMER | H14: 06/26/2023 | I14: 24 | J14: Carlo Damelio | L14: =_xlfn.XLOOKUP(A14,S70Sheet!A:A,S70Sheet!A:A)
A15: B5Y211017 | B15: S70 T4 V2 | C15: Bingham Equipment Co, Tucson, AZ-01075, TUCSON, AZ | D15: Southwest Equipment LLC | E15: CUSTOMER | H15: 05/27/2023 | I15: 24 | J15: Victor Lopez | L15: =_xlfn.XLOOKUP(A15,S70Sheet!A:A,S70Sheet!A:A)
A16: B5Y211018 | B16: S70 T4 V2 | C16: Bingham Equipment Co, Tucson, AZ-01075, TUCSON, AZ | D16: Desert Valley Landscaping | E16: CUSTOMER | H16: 06/09/2023 | I16: 24 | J16: Victor Lopez | L16: =_xlfn.XLOOKUP(A16,S70Sheet!A:A,S70Sheet!A:A)
A17: B5Y211019 | B17: S70 T4 V2 | C17: HERC RENTALS - 09722-N000298, Fife, WA | D17: HERC RENTALS - 09722-N000298, Fife, WA | E17: NATIONALACCOUNT | H17: 11/17/2023 | I17: 18 | L17: =_xlfn.XLOOKUP(A17,S70Sheet!A:A,S70Sheet!A:A)
A18: B5Y211020 | B18: S70 T4 V2 | C18: Bobcat of Miami, Hialeah Gardens, FL-03010, DORAL, FL | D18: equipment and tools solution | E18: CUSTOMER | H18: 06/19/2023 | I18: 24 | J18: Lucas DeSouza | L18: =_xlfn.XLOOKUP(A18,S70Sheet!A:A,S70Sheet!A:A)
A19: B5Y211021 | B19: S70 T4 V2 | C19: HERC RENTALS - 09633-N000335, N Hollywood, CA | D19: HERC RENTALS - 09633-N000335, N Hollywood, CA | E19: NATIONALACCOUNT | H19: 11/21/2023 | I19: 18 | L19: =_xlfn.XLOOKUP(A19,S70Sheet!A:A,S70Sheet!A:A)
A20: B5Y211022 | B20: S70 T4 V2 | C20: HERC RENTALS - 09644-N000644, Fresno, CA | D20: HERC RENTALS - 09644-N000644, Fresno, CA | E20: NATIONALACCOUNT | H20: 11/20/2023 | I20: 18 | L20: =_xlfn.XLOOKUP(A20,S70Sheet!A:A,S70Sheet!A:A)
A21: B5Y211023 | B21: S70 T4 V2 | C21: Bobcat of Los Angeles., Cerritos, CA-06879, CERRITOS, CA | D21: ZR Equipment Rentals, LLC | E21: CUSTOMER | H21: 10/27/2023 | I21: 19 | J21: Benjamin Nunez | L21: =_xlfn.XLOOKUP(A21,S70Sheet!A:A,S70Sheet!A:A)
A22: B5Y211024 | B22: S70 T4 V2 | C22: Bobcat of New York City, Maspeth, NY-08828, MASPETH, NY | D22: paul johnson custom bldg | E22: CUSTOMER | H22: 06/21/2023 | I22: 24 | J22: Jim Badaracco | L22: =_xlfn.XLOOKUP(A22,S70Sheet!A:A,S70Sheet!A:A)
A23: B5Y211025 | B23: S70 T4 V2 | C23: HERC RENTALS - 09661-N001678, Las Vegas, NV | D23: HERC RENTALS - 09661-N001678, Las Vegas, NV | E23: NATIONALACCOUNT | H23: 11/21/2023 | I23: 18 | L23: =_xlfn.XLOOKUP(A23,S70Sheet!A:A,S70Sheet!A:A)
A24: B5Y211026 | B24: S70 T4 V2 | C24: Bingham Equipment Co, Mesa, AZ-01056, MESA, AZ | D24: Victor Alvarez | E24: CUSTOMER | H24: 06/07/2023 | I24: 24 | J24: Brandon Townsend | L24: =_xlfn.XLOOKUP(A24,S70Sheet!A:A,S70Sheet!A:A)
A25: B5Y211027 | B25: S70 T4 V2 | C25: Bobcat of Los Angeles., Cerritos, CA-06879, CERRITOS, CA | D25: FP CONCRETE | E25: CUSTOMER | H25: 06/09/2023 | I25: 24 | J25: Benjamin Nunez | L25: =_xlfn.XLOOKUP(A25,S70Sheet!A:A,S70Sheet!A:A)
A26: B5Y211028 | B26: S70 T4 V2 | C26: Valley Bobcat, Sun Valley, CA-09467, SUN VALLEY, CA | D26: Charlie & Sons Trucking | E26: CUSTOMER | H26: 05/24/2023 | I26: 24 | J26: Jonpierre Rejas | L26: =_xlfn.XLOOKUP(A26,S70Sheet!A:A,S70Sheet!A:A)
A27: B5Y211029 | B27: S70 T4 V2 | C27: Bobcat of Las Vegas, North Las Vegas, NV-01127, NORTH LAS VEGAS, NV | D27: ALPHA LANDSCAPES | E27: CUSTOMER | H27: 06/19/2023 | I27: 24 | J27: Carlo Damelio | L27: =_xlfn.XLOOKUP(A27,S70Sheet!A:A,S70Sheet!A:A)
A28: B5Y211030 | B28: S70 T4 V2 | C28: Bobcat of Fremont, Fremont, CA-05319, FREMONT, CA | D28: ARTLAND | E28: CUSTOMER | H28: 06/05/2023 | I28: 24 | J28: Luis Martinez | L28: =_xlfn.XLOOKUP(A28,S70Sheet!A:A,S70Sheet!A:A)
A29: B5Y211031 | B29: S70 T4 V2 | C29: Inland Bobcat, Riverside, CA-03080, RIVERSIDE, CA | D29: Paul Cantor | E29: CUSTOMER | H29: 05/17/2023 | I29: 24 | J29: Hector Sanchez | L29: =_xlfn.XLOOKUP(A29,S70Sheet!A:A,S70Sheet!A:A)
A30: B5Y211032 | B30: S70 T4 V2 | C30: Valley Bobcat, Sun Valley, CA-09467, SUN VALLEY, CA | D30: Server Construction, Inc. | E30: CUSTOMER | H30: 05/23/2023 | I30: 24 | J30: Jonpierre Rejas | L30: =_xlfn.XLOOKUP(A30,S70Sheet!A:A,S70Sheet!A:A)
A31: B5Y211033 | B31: S70 T4 V2 | C31: Bobcat of Albuquerque, Albuquerque, NM-00574, ALBUQUERQUE, NM | D31: FRANKS SUPPLY CO INC | E31: CUSTOMER | H31: 06/27/2023 | I31: 23 | J31: Miguel Merino | L31: =_xlfn.XLOOKUP(A31,S70Sheet!A:A,S70Sheet!A:A)
A32: B5Y211034 | B32: S70 T4 V2 | C32: Bobcat of Lakeland, Lakeland, FL-08946, LAKELAND, FL | D32: RINKER MATERIALS | E32: CUSTOMER | H32: 08/21/2023 | I32: 24 | J32: Tim Wellman | L32: =_xlfn.XLOOKUP(A32,S70Sheet!A:A,S70Sheet!A:A)
A33: B5Y211035 | B33: S70 T4 V2 | C33: Inland Bobcat, Riverside, CA-03080, RIVERSIDE, CA | D33: ROSOCA CONSTRUCTION CO | E33: CUSTOMER | H33: 05/30/2023 | I33: 24 | J33: Art Mata | L33: =_xlfn.XLOOKUP(A33,S70Sheet!A:A,S70Sheet!A:A)
A34: B5Y211036 | B34: S70 T4 V2 | C34: Bobcat of the Rockies, Colorado Springs, CO-00528, COLORADO SPRINGS, CO | D34: BILLS TOOL RENTAL | E34: CUSTOMER | H34: 05/25/2023 | I34: 24 | J34: Daniel Hankins | L34: =_xlfn.XLOOKUP(A34,S70Sheet!A:A,S70Sheet!A:A)
A35: B5Y211037 | B35: S70 T4 V2 | C35: Bingham Equipment Co, Buckeye, AZ-01068, BUCKEYE, AZ | D35: GC 360 LLC | E35: CUSTOMER | H35: 06/27/2023 | I35: 24 | J35: Josh Rodriguez | L35: =_xlfn.XLOOKUP(A35,S70Sheet!A:A,S70Sheet!A:A)
... A48: B5Y211051 | B48: S70 T4 V2 | C48: Bobcat of Anderson, Anderson, IN-00513, ANDERSON, IN | D48: BECK'S - TOM HOOPER-N107059, Atlanta, IN | E48: NATIONALACCOUNT | H48: 06/23/2023 | I48: 23 | J48: Chris Wooldridge | L48: =_xlfn.XLOOKUP(A48,S70Sheet!A:A,S70Sheet!A:A)
A49: B5Y211052 | B49: S70 T4 V2 | C49: COOPER EQUIPMENT RENTALS LTD-2793331, MISSISSAUGA, ON | D49: COOPER EQUIPMENT RENTALS LTD-2793331, MISSISSAUGA, ON | E49: NATIONALACCOUNT | H49: 07/28/2023 | I49: 22 | L49: =_xlfn.XLOOKUP(A49,S70Sheet!A:A,S70Sheet!A:A)
A50: B5Y211053 | B50: S70 T4 V2 | C50: Bobcat of the Rockies, Parker, CO-00527, PARKER, CO | D50: KELLEY SPRINKLER AND LANDSCAPE | E50: CUSTOMER | H50: 06/15/2023 | I50: 24 | J50: Rollie McDaniel | L50: =_xlfn.XLOOKUP(A50,S70Sheet!A:A,S70Sheet!A:A)
A51: B5Y211054 | B51: S70 T4 V2 | C51: UNITED RENTALS 801-N96333, Everett, MA | D51: UNITED RENTALS 801-N96333, Everett, MA | E51: NATIONALACCOUNT | H51: 08/08/2023 | I51: 21 | L51: =_xlfn.XLOOKUP(A51,S70Sheet!A:A,S70Sheet!A:A)
A52: B5Y211055 | B52: S70 T4 V2 | C52: Bobcat of West Chester, West Chester, PA-00280, WEST CHESTER, PA | D52: Guizzetti & SOns | E52: CUSTOMER | H52: 12/06/2023 | I52: 20 | J52: Fred Ferrentino | L52: =_xlfn.XLOOKUP(A52,S70Sheet!A:A,S70Sheet!A:A)
A53: B5Y211056 | B53: S70 T4 V2 | C53: Equipment World Inc., Thunder Bay, ON-02845, THUNDER BAY, ON | D53: JMF Northern Consulting | E53: CUSTOMER | H53: 12/22/2023 | I53: 19 | J53: Jonathon Soares | L53: =_xlfn.XLOOKUP(A53,S70Sheet!A:A,S70Sheet!A:A)
A54: B5Y211057 | B54: S70 T4 V2 | C54: Flagstaff Equipment Co Inc, Flagstaff, AZ-03350, FLAGSTAFF, AZ | D54: Phillip Aerts | E54: CUSTOMER | H54: 10/05/2023 | I54: 20 | J54: Chuck Clanton | L54: =_xlfn.XLOOKUP(A54,S70Sheet!A:A,S70Sheet!A:A)
A55: B5Y211058 | B55: S70 T4 V2 | C55: Bobcat of North Jersey, Totowa, NJ-07333, TOTOWA, NJ | D55: Passaic County Community College | E55: CUSTOMER | H55: 11/30/2023 | I55: 22 | J55: Anthony Tudda | L55: =_xlfn.XLOOKUP(A55,S70Sheet!A:A,S70Sheet!A:A)
A56: B5Y211059 | B56: S70 T4 V2 | C56: Bingham Equipment Co, Mesa, AZ-01056, MESA, AZ | D56: SUNBELT RENTALS - PC0523-N003829, Phoenix, AZ | E56: NATIONALACCOUNT | H56: 06/28/2023 | I56: 24 | J56: Nate Stanton | L56: =_xlfn.XLOOKUP(A56,S70Sheet!A:A,S70Sheet!A:A)
A57: B5Y211060 | B57: S70 T4 V2 | C57: Bingham Equipment Co, Mesa, AZ-01056, MESA, AZ | D57: Teresa Bautista | E57: CUSTOMER | H57: 05/30/2023 | I57: 24 | J57: Brandon Townsend | L57: =_xlfn.XLOOKUP(A57,S70Sheet!A:A,S70Sheet!A:A)
A58: B5Y211061 | B58: S70 T4 V2 | C58: Bingham Equipment Co, Mesa, AZ-01056, MESA, AZ | D58: A to Z Equipment Rentals | E58: CUSTOMER | H58: 06/20/2023 | I58: 24 | J58: Nate Stanton | L58: =_xlfn.XLOOKUP(A58,S70Sheet!A:A,S70Sheet!A:A)
A59: B5Y211062 | B59: S70 T4 V2 | C59: Bingham Equipment Co, Tucson, AZ-01075, TUCSON, AZ | D59: Landscape Solutions of Tucson LLC | E59: CUSTOMER | H59: 06/02/2023 | I59: 24 | J59: Victor Lopez | L59: =_xlfn.XLOOKUP(A59,S70Sheet!A:A,S70Sheet!A:A)
A60: B5Y211063 | B60: S70 T4 V2 | C60: Bobcat of San Antonio, San Antonio, TX-07742, SAN ANTONIO, TX | D60: Robles 1, LLC | E60: CUSTOMER | H60: 08/25/2023 | I60: 23 | J60: David Schumann | L60: =_xlfn.XLOOKUP(A60,S70Sheet!A:A,S70Sheet!A:A)
A61: B5Y211064 | B61: S70 T4 V2 | C61: Bobcat of Phoenix, Phoenix, AZ-01055, PHOENIX, AZ | D61: MasterAZscapes LLC | E61: CUSTOMER | H61: 06/12/2023 | I61: 24 | J61: Gary Walker | L61: =_xlfn.XLOOKUP(A61,S70Sheet!A:A,S70Sheet!A:A)
A62: B5Y211065 | B62: S70 T4 V2 | C62: Bobcat of the Rockies, Colorado Springs, CO-00528, COLORADO SPRINGS, CO | D62: BILLS TOOL RENTAL | E62: CUSTOMER | H62: 05/25/2023 | I62: 24 | J62: Daniel Hankins | L62: =_xlfn.XLOOKUP(A62,S70Sheet!A:A,S70Sheet!A:A)
A63: B5Y211067 | B63: S70 T4 V2 | C63: Berchtold Equipment Co, Bakersfield, CA-00927, BAKERSFIELD, CA | D63: DO IT BEST - 6089-N106960, Rosamond, CA | E63: NATIONALACCOUNT | H63: 05/18/2023 | I63: 24 | J63: Terry Spencer | L63: =_xlfn.XLOOKUP(A63,S70Sheet!A:A,S70Sheet!A:A)
... A76: B5Y211080 | B76: S70 T4 V2 | C76: Bobcat of San Antonio, San Antonio, TX-07742, SAN ANTONIO, TX | D76: WATSONSUPERSTORE OF SAN ANTONIO INC. | E76: CUSTOMER | H76: 06/12/2023 | I76: 23 | J76: Eli Esquivel | L76: =_xlfn.XLOOKUP(A76,S70Sheet!A:A,S70Sheet!A:A)
A77: B5Y211081 | B77: S70 T4 V2 | C77: SUNSTATE EQUIPMENT - BWP-N95511, Baldwin Park, CA | D77: SUNSTATE EQUIPMENT - BWP-N95511, Baldwin Park, CA | E77: NATIONALACCOUNT | H77: 06/01/2023 | I77: 23 | L77: =_xlfn.XLOOKUP(A77,S70Sheet!A:A,S70Sheet!A:A)
A78: B5Y211082 | B78: S70 T4 V2 | C78: K.C. Bobcat, Olathe, KS-05287, OLATHE, KS | D78: Tompkins Agricultural Industries LLC | E78: CUSTOMER | H78: 10/20/2023 | I78: 23 | J78: Derek Diederich | L78: =_xlfn.XLOOKUP(A78,S70Sheet!A:A,S70Sheet!A:A)
A79: B5Y211083 | B79: S70 T4 V2 | C79: Bobcat of Motor City East, Chesterfield, MI-01035, CHESTERFIELD, MI | D79: Max Demolition | E79: CUSTOMER | H79: 06/02/2023 | I79: 24 | J79: Ray Henwood | L79: =_xlfn.XLOOKUP(A79,S70Sheet!A:A,S70Sheet!A:A)
A80: B5Y211084 | B80: S70 T4 V2 | C80: Bobcat of Reno, Reno, NV-01933, SPARKS, NV | D80: QUALITY INYO CONCRETE | E80: CUSTOMER | H80: 06/20/2023 | I80: 24 | J80: Karl Tremblay | L80: =_xlfn.XLOOKUP(A80,S70Sheet!A:A,S70Sheet!A:A)
A81: B5Y211085 | B81: S70 T4 V2 | C81: Bobcat of Ventura, Ventura, CA-08744, VENTURA, CA | D81: AGUILERA SVC INC | E81: CUSTOMER | H81: 05/25/2023 | I81: 24 | J81: Randy Dvorak | L81: =_xlfn.XLOOKUP(A81,S70Sheet!A:A,S70Sheet!A:A)
A82: B5Y211087 | B82: S70 T4 V2 | C82: K.C. Bobcat, Olathe, KS-05287, OLATHE, KS | D82: The Monarch Cement Company | E82: CUSTOMER | H82: 05/30/2023 | I82: 24 | J82: Derek Diederich | L82: =_xlfn.XLOOKUP(A82,S70Sheet!A:A,S70Sheet!A:A)
A83: B5Y211088 | B83: S70 T4 V2 | C83: Bobcat of North Texas - Lewisville, Lewisville, TX-00656, LEWISVILLE, TX | D83: J&P Tree | E83: CUSTOMER | H83: 12/19/2023 | I83: 24 | J83: Nick Ford | L83: =_xlfn.XLOOKUP(A83,S70Sheet!A:A,S70Sheet!A:A)
A84: B5Y211089 | B84: S70 T4 V2 | C84: Bobcat of Chattanooga, Chattanooga, TN-09466, CHATTANOOGA, TN | D84: JACKIE EVANS FARMS | E84: CUSTOMER | H84: 12/29/2023 | I84: 24 | J84: Joshua Freeman | L84: =_xlfn.XLOOKUP(A84,S70Sheet!A:A,S70Sheet!A:A)
A85: B5Y211090 | B85: S70 T4 V2 | C85: Bobcat of Contra Costa, Pittsburg, CA-01845, PITTSBURG, CA | D85: JAC CONSTRUCTION | E85: CUSTOMER | H85: 07/14/2023 | I85: 24 | J85: Jay Alias | L85: =_xlfn.XLOOKUP(A85,S70Sheet!A:A,S70Sheet!A:A)
A86: B5Y211091 | B86: S70 T4 V2 | C86: Bingham Equipment Co, Mesa, AZ-01056, MESA, AZ | D86: A to Z Equipment Rentals | E86: CUSTOMER | H86: 06/20/2023 | I86: 24 | J86: Nate Stanton | L86: =_xlfn.XLOOKUP(A86,S70Sheet!A:A,S70Sheet!A:A)
A87: B5Y211092 | B87: S70 T4 V2 | C87: Bobcat of Las Vegas, North Las Vegas, NV-01127, NORTH LAS VEGAS, NV | D87: ALPHA LANDSCAPES | E87: CUSTOMER | H87: 06/19/2023 | I87: 24 | J87: Carlo Damelio | L87: =_xlfn.XLOOKUP(A87,S70Sheet!A:A,S70Sheet!A:A)
A88: B5Y211093 | B88: S70 T4 V2 | C88: Bobcat of Houston, Baytown, TX-09685, BAYTOWN, TX | D88: G.C. HOMES AND INVESTMENTS LLC | E88: CUSTOMER | H88: 05/26/2023 | I88: 24 | J88: Josh Kimich | L88: =_xlfn.XLOOKUP(A88,S70Sheet!A:A,S70Sheet!A:A)
A89: B5Y211094 | B89: S70 T4 V2 | C89: Bingham Equipment Co, Mesa, AZ-01056, MESA, AZ | D89: GDL CONSTRUCTION PRO LLC | E89: CUSTOMER | H89: 06/20/2023 | I89: 24 | J89: Ashley Ghose | L89: =_xlfn.XLOOKUP(A89,S70Sheet!A:A,S70Sheet!A:A)
... A96: B5Y211101 | B96: S70 T4 V2 | C96: K.C. Bobcat, Olathe, KS-05287, OLATHE, KS | D96: JOSE GUILLEN | E96: CUSTOMER | H96: 02/28/2024 | I96: 24 | J96: Andrew Drummond | L96: =_xlfn.XLOOKUP(A96,S70Sheet!A:A,S70Sheet!A:A)
A97: B5Y211102 | B97: S70 T4 V2 | C97: SUNSTATE EQUIPMENT - BWP-N95511, Baldwin Park, CA | D97: SUNSTATE EQUIPMENT - BWP-N95511, Baldwin Park, CA | E97: NATIONALACCOUNT | H97: 06/01/2023 | I97: 23 | L97: =_xlfn.XLOOKUP(A97,S70Sheet!A:A,S70Sheet!A:A)
A98: B5Y211103 | B98: S70 T4 V2 | C98: SUNSTATE EQUIPMENT - PEO-N002423, Peoria, AZ | D98: SUNSTATE EQUIPMENT - PEO-N002423, Peoria, AZ | E98: NATIONALACCOUNT | H98: 06/05/2023 | I98: 23 | L98: =_xlfn.XLOOKUP(A98,S70Sheet!A:A,S70Sheet!A:A)
A99: B5Y211104 | B99: S70 T4 V2 | C99: Bobcat of Gilroy, Gilroy, CA-02814, GILROY, CA | D99: Quynh Ngo | E99: CUSTOMER | H99: 05/23/2023 | I99: 24 | J99: Alex Serdiuk | L99: =_xlfn.XLOOKUP(A99,S70Sheet!A:A,S70Sheet!A:A)
A100: B5Y211105 | B100: S70 T4 V2 | C100: Bobcat of New York City, Maspeth, NY-08828, MASPETH, NY | D100: paul johnson custom bldg | E100: CUSTOMER | H100: 06/23/2023 | I100: 24 | J100: Jim Badaracco | L100: =_xlfn.XLOOKUP(A100,S70Sheet!A:A,S70Sheet!A:A)
A101: B5Y211106 | B101: S70 T4 V2 | C101: Bobcat of Las Vegas, North Las Vegas, NV-01127, NORTH LAS VEGAS, NV | D101: ALPHA LANDSCAPES | E101: CUSTOMER | H101: 06/19/2023 | I101: 24 | J101: Carlo Damelio | L101: =_xlfn.XLOOKUP(A101,S70Sheet!A:A,S70Sheet!A:A)
A102: B5Y211107 | B102: S70 T4 V2 | C102: Bobcat of Gilroy, Gilroy, CA-02814, GILROY, CA | D102: Quynh Ngo | E102: CUSTOMER | H102: 06/20/2023 | I102: 23 | J102: Alex Serdiuk | L102: =_xlfn.XLOOKUP(A102,S70Sheet!A:A,S70Sheet!A:A)
A103: B5Y211108 | B103: S70 T4 V2 | C103: Bobcat of Las Vegas, North Las Vegas, NV-01127, NORTH LAS VEGAS, NV | D103: ALPHA LANDSCAPES | E103: CUSTOMER | H103: 06/19/2023 | I103: 24 | J103: Carlo Damelio | L103: =_xlfn.XLOOKUP(A103,S70Sheet!A:A,S70Sheet!A:A)
A104: B5Y211109 | B104: S70 T4 V2 | C104: Bobcat of Atlanta, Riverdale, GA-00403, RIVERDALE, GA | D104: MCB LANDSCAPING INC | E104: CUSTOMER | H104: 12/29/2023 | I104: 23 | J104: John Willett | L104: =_xlfn.XLOOKUP(A104,S70Sheet!A:A,S70Sheet!A:A)
A105: B5Y211110 | B105: S70 T4 V2 | C105: Bobcat of New York City, Maspeth, NY-08828, MASPETH, NY | D105: paul johnson custom bldg | E105: CUSTOMER | H105: 06/23/2023 | I105: 24 | J105: Jim Badaracco | L105: =_xlfn.XLOOKUP(A105,S70Sheet!A:A,S70Sheet!A:A)
A106: B5Y211111 | B106: S70 T4 V2 | C106: Bobcat of Las Vegas, North Las Vegas, NV-01127, NORTH LAS VEGAS, NV | D106: ALPHA LANDSCAPES | E106: CUSTOMER | H106: 06/19/2023 | I106: 24 | J106: Carlo Damelio | L106: =_xlfn.XLOOKUP(A106,S70Sheet!A:A,S70Sheet!A:A)
A107: B5Y211112 | B107: S70 T4 V2 | C107: Bobcat of Ventura, Ventura, CA-08744, VENTURA, CA | D107: Centerpoint | E107: CUSTOMER | H107: 06/30/2023 | I107: 23 | J107: Jeff Wright | L107: =_xlfn.XLOOKUP(A107,S70Sheet!A:A,S70Sheet!A:A)
A108: B5Y211113 | B108: S70 T4 V2 | C108: SUNSTATE EQUIPMENT - DNV-N002683, Commerce City, CO | D108: SUNSTATE EQUIPMENT - DNV-N002683, Commerce City, CO | E108: NATIONALACCOUNT | H108: 05/31/2023 | I108: 24 | L108: =_xlfn.XLOOKUP(A108,S70Sheet!A:A,S70Sheet!A:A)
A109: B5Y211115 | B109: S70 T4 V2 | C109: Bobcat of El Paso, El Paso, TX-00573, EL PASO, TX | D109: Southwest Trucks and Equipment | E109: CUSTOMER | H109: 06/09/2023 | I109: 24 | J109: James Napier | L109: =_xlfn.XLOOKUP(A109,S70Sheet!A:A,S70Sheet!A:A)
A110: B5Y211116 | B110: S70 T4 V2 | C110: Bobcat of New York City, Maspeth, NY-08828, MASPETH, NY | D110: paul johnson custom bldg | E110: CUSTOMER | H110: 06/16/2023 | I110: 24 | J110: Jim Badaracco | L110: =_xlfn.XLOOKUP(A110,S70Sheet!A:A,S70Sheet!A:A)
A111: B5Y211117 | B111: S70 T4 V2 | C111: South Coast Bobcat, Orange, CA-08461, ORANGE, CA | D111: Ayala Landscape | E111: CUSTOMER | H111: 06/29/2023 | I111: 24 | J111: Dan Arevalo | L111: =_xlfn.XLOOKUP(A111,S70Sheet!A:A,S70Sheet!A:A)
A112: B5Y211119 | B112: S70 T4 V2 | C112: Bobcat of Marble Falls, Marble Falls, TX-07305, Marble Falls, TX | D112: Casaperior, LLC. | E112: CUSTOMER | H112: 07/13/2023 | I112: 23 | J112: Danny Lopez | L112: =_xlfn.XLOOKUP(A112,S70Sheet!A:A,S70Sheet!A:A)
A113: B5Y211120 | B113: S70 T4 V2 | C113: Bobcat of El Paso, El Paso, TX-00573, EL PASO, TX | D113: RUBEN SIMENTAL | E113: CUSTOMER | H113: 06/15/2023 | I113: 24 | J113: James Napier | L113: =_xlfn.XLOOKUP(A113,S70Sheet!A:A,S70Sheet!A:A)
A114: B5Y211121 | B114: S70 T4 V2 | C114: Bobcat of El Paso, El Paso, TX-00573, EL PASO, TX | D114: G C HOMES & INVST LLC | E114: CUSTOMER | H114: 06/23/2023 | I114: 24 | J114: James Napier | L114: =_xlfn.XLOOKUP(A114,S70Sheet!A:A,S70Sheet!A:A)
A115: B5Y211122 | B115: S70 T4 V2 | C115: Bobcat of Los Angeles., Cerritos, CA-06879, CERRITOS, CA | D115: HRL INC, DBA HD EQUIPMENT | E115: CUSTOMER | H115: 10/12/2023 | I115: 20 | J115: Benjamin Nunez | L115: =_xlfn.XLOOKUP(A115,S70Sheet!A:A,S70Sheet!A:A)
A116: B5Y211124 | B116: S70 T4 V2 | C116: Bobcat of Houston/Pearland, Houston, TX-00553, HOUSTON, TX | D116: SAVAGE SERVICES CORPORATION | E116: CUSTOMER | H116: 06/08/2023 | I116: 23 | J116: Roland Carrion | L116: =_xlfn.XLOOKUP(A116,S70Sheet!A:A,S70Sheet!A:A)
A117: B5Y211125 | B117: S70 T4 V2 | C117: Bobcat of Miami, Hialeah Gardens, FL-03010, DORAL, FL | D117: RR LAWN CARE & LANDSCAPE SERVICES LLC | E117: CUSTOMER | H117: 06/19/2023 | I117: 23 | J117: Lucas DeSouza | L117: =_xlfn.XLOOKUP(A117,S70Sheet!A:A,S70Sheet!A:A)
A118: B5Y211126 | B118: S70 T4 V2 | C118: Bingham Equipment Co, Tucson, AZ-01075, TUCSON, AZ | D118: SANTA RITA LANDSCAPING | E118: CUSTOMER | H118: 07/31/2023 | I118: 23 | J118: Victor Lopez | L118: =_xlfn.XLOOKUP(A118,S70Sheet!A:A,S70Sheet!A:A)
A119: B5Y211127 | B119: S70 T4 V2 | C119: Bobcat of Salem, Salem, OR-02108, SALEM, OR | D119: CHARLENE ROBERTS | E119: CUSTOMER | H119: 10/18/2023 | I119: 23 | J119: Nathan Leao | L119: =_xlfn.XLOOKUP(A119,S70Sheet!A:A,S70Sheet!A:A)
A120: B5Y211128 | B120: S70 T4 V2 | C120: Bobcat of Salem, Salem, OR-02108, SALEM, OR | D120: Covanta-Marion County | E120: CUSTOMER | H120: 07/07/2023 | I120: 23 | J120: Nathan Leao | L120: =_xlfn.XLOOKUP(A120,S70Sheet!A:A,S70Sheet!A:A)
... A122: B5Y211130 | B122: S70 T4 V2 | C122: Flagstaff Equipment Co Inc, Flagstaff, AZ-03350, FLAGSTAFF, AZ | D122: Las Perlas Landscaping, LLC | E122: CUSTOMER | H122: 06/30/2023 | I122: 23 | J122: Chuck Clanton | L122: =_xlfn.XLOOKUP(A122,S70Sheet!A:A,S70Sheet!A:A)
A123: B5Y211131 | B123: S70 T4 V2 | C123: SUNSTATE EQUIPMENT - TUC-N002782, Tucson, AZ | D123: SUNSTATE EQUIPMENT - TUC-N002782, Tucson, AZ | E123: NATIONALACCOUNT | H123: 06/05/2023 | I123: 23 | L123: =_xlfn.XLOOKUP(A123,S70Sheet!A:A,S70Sheet!A:A)
A124: B5Y211132 | B124: S70 T4 V2 | C124: Bobcat of Miami, Hialeah Gardens, FL-03010, DORAL, FL | D124: ROBERTOS BOBCAT INC | E124: CUSTOMER | H124: 06/28/2023 | I124: 23 | J124: Jerry Alberti | L124: =_xlfn.XLOOKUP(A124,S70Sheet!A:A,S70Sheet!A:A)
A125: B5Y211133 | B125: S70 T4 V2 | C125: Bobcat of Sacramento, Sacramento, CA-01873, SACRAMENTO, CA | D125: MARTIN MARTINEZ PADILLA | E125: CUSTOMER | H125: 07/21/2023 | I125: 23 | J125: Randy Erwin | L125: =_xlfn.XLOOKUP(A125,S70Sheet!A:A,S70Sheet!A:A)
A126: B5Y211134 | B126: S70 T4 V2 | C126: Bingham Equipment Co, Mesa, AZ-01056, MESA, AZ | D126: Mow Power Inc | E126: CUSTOMER | H126: 06/28/2023 | I126: 23 | J126: Nate Stanton | L126: =_xlfn.XLOOKUP(A126,S70Sheet!A:A,S70Sheet!A:A)
A127: B5Y211135 | B127: S70 T4 V2 | C127: SUNSTATE EQUIPMENT - BWP-N95511, Baldwin Park, CA | D127: SUNSTATE EQUIPMENT - BWP-N95511, Baldwin Park, CA | E127: NATIONALACCOUNT | H127: 06/01/2023 | I127: 23 | L127: =_xlfn.XLOOKUP(A127,S70Sheet!A:A,S70Sheet!A:A)
A128: B5Y211136 | B128: S70 T4 V2 | C128: Bobcat of Omaha, Omaha, NE-07415, OMAHA, NE | D128: Honeyman Rent-All | E128: CUSTOMER | H128: 06/27/2023 | I128: 23 | J128: Dustin Goodsell | L128: =_xlfn.XLOOKUP(A128,S70Sheet!A:A,S70Sheet!A:A)
A129: B5Y211137 | B129: S70 T4 V2 | C129: SUNSTATE EQUIPMENT - VEG-N002652, Henderson, NV | D129: SUNSTATE EQUIPMENT - VEG-N002652, Henderson, NV | E129: NATIONALACCOUNT | H129: 06/06/2023 | I129: 23 | L129: =_xlfn.XLOOKUP(A129,S70Sheet!A:A,S70Sheet!A:A)
A130: B5Y211138 | B130: S70 T4 V2 | C130: K.C. Bobcat, Blue Springs, MO-05288, BLUE SPRINGS, MO | D130: FRIENDS OF THE ZOO INC KCMO | E130: CUSTOMER | H130: 12/26/2023 | I130: 23 | J130: Jim Hicks | L130: =_xlfn.XLOOKUP(A130,S70Sheet!A:A,S70Sheet!A:A)
A131: B5Y211139 | B131: S70 T4 V2 | C131: Bobcat of Fresno, Fresno, CA-01119, FRESNO, CA | D131: SALAS CONCRETE INC | E131: CUSTOMER | H131: 08/24/2023 | I131: 23 | J131: Ryan Wilson | L131: =_xlfn.XLOOKUP(A131,S70Sheet!A:A,S70Sheet!A:A)
...

Sheet Sheet4
B2: Dealer Name
B3: Abhishek Megamech Private Limited-C14753-BLC, FARIDABAD, HP
B4: Advantage Farm Equipment Ltd, Wyoming, ON-01520, Wyoming, ON
B5: Ag-Plus Mechanical Ltd., Medicine Hat, AB-00070, MEDICINE HAT, AB
B6: Agrikom, Mirabel, QC-00302, Mirabel, QC
B7: ASHA INFRACORE-C07923-BC, BANGALORE, KARNATAKA
B8: ASHA INFRACORE-C07923-BLC, Bangalore
B9: Atlas Bobcat, Elk Grove Village, IL-00450, ELK GROVE VILLAGE, IL
B10: Atlas Bobcat, Elk Grove Village., IL-00450, ELK GROVE VILLAGE, IL
B11: Atlas Bobcat, Mokena, IL-00275, MOKENA, IL
B12: Atlas Bobcat, Wauconda, IL-02198, WAUCONDA, IL
B13: Atlas Bobcat, West Chicago, IL-00306, WEST CHICAGO, IL
... B510: YOLO EXIMCARE PRIVATE LIMITED-C14775-BLC, Ranchi, JK
